[{"_id": "101945@1573837053", "videoPointerID": null, "mode": 1, "spinClockTiltHour": 9, "spinClockTiltMinute": 8, "horizontalAngle": "-1.9", "launchAngle": 1.828293, "rifleSpin": 1872.97913, "pitch_id": 1573837053, "_day": 15, "_month": 11, "_year": 2019, "_hour": 16, "_minute": 57, "_second": 33, "_milisecond": 0, "speed": 76.8, "spin": 2247, "trueSpin": 1242, "spinEfficiency": 55.3, "spinConfidence": 0.951705337, "releaseHeight": 3.4008427545131132, "releaseSide": 2.53662697235961, "releaseExtension": "-", "pitchType": 0, "horizontalBreak": 12, "verticalBreak": 0.1, "strike": "N", "szx": 18.8, "szy": 12.5, "no": 1, "date": "15 NOV 19", "date_original": "2019-11-15T16:57:33.000Z", "truespin": 1242, "selected": false, "spinAxis": "02h:52m", "gyroDegree": "56.5"}, {"_id": "101945@1573837010", "videoPointerID": null, "mode": 1, "spinClockTiltHour": 10, "spinClockTiltMinute": 0, "horizontalAngle": "-3.1", "launchAngle": 1.487467, "rifleSpin": 2125.63647, "pitch_id": 1573837010, "_day": 15, "_month": 11, "_year": 2019, "_hour": 16, "_minute": 56, "_second": 50, "_milisecond": 0, "speed": 73.4, "spin": 2194, "trueSpin": 0, "spinEfficiency": 0, "spinConfidence": 0, "releaseHeight": 3.133512002794434, "releaseSide": 2.3967659354016146, "releaseExtension": "-", "pitchType": 4, "horizontalBreak": 0, "verticalBreak": 0, "strike": "N", "szx": -7.1, "szy": -5.7, "no": 2, "date": "15 NOV 19", "date_original": "2019-11-15T16:56:50.000Z", "truespin": 0, "selected": false, "spinAxis": 0, "gyroDegree": "90.0"}, {"_id": "101945@1573836991", "videoPointerID": null, "mode": 1, "spinClockTiltHour": 9, "spinClockTiltMinute": 10, "horizontalAngle": "-3.0", "launchAngle": 3.084672, "rifleSpin": 1776.99524, "pitch_id": 1573836991, "_day": 15, "_month": 11, "_year": 2019, "_hour": 16, "_minute": 56, "_second": 31, "_milisecond": 0, "speed": 77.3, "spin": 2158, "trueSpin": 1224, "spinEfficiency": 56.7, "spinConfidence": 0.938186646, "releaseHeight": 3.3057639485943153, "releaseSide": 2.58770144750286, "releaseExtension": "-", "pitchType": 0, "horizontalBreak": 11.7, "verticalBreak": 0.1, "strike": "Y", "szx": 5.8, "szy": 28.4, "no": 3, "date": "15 NOV 19", "date_original": "2019-11-15T16:56:31.000Z", "truespin": 1224, "selected": false, "spinAxis": "02h:50m", "gyroDegree": "55.4"}, {"_id": "101945@1573836909", "videoPointerID": null, "mode": 1, "spinClockTiltHour": 11, "spinClockTiltMinute": 50, "horizontalAngle": "-1.5", "launchAngle": 3.37631035, "rifleSpin": 2099.07251, "pitch_id": 1573836909, "_day": 15, "_month": 11, "_year": 2019, "_hour": 16, "_minute": 55, "_second": 9, "_milisecond": 0, "speed": 68.7, "spin": 2166, "trueSpin": 534, "spinEfficiency": 24.7, "spinConfidence": 0.927329957, "releaseHeight": 2.97448228798578, "releaseSide": 2.4646035667383237, "releaseExtension": "-", "pitchType": 4, "horizontalBreak": -0.8, "verticalBreak": 5.2, "strike": "N", "szx": 13.2, "szy": 15.9, "no": 4, "date": "15 NOV 19", "date_original": "2019-11-15T16:55:09.000Z", "truespin": 534, "selected": false, "spinAxis": "00h:10m", "gyroDegree": "75.7"}, {"_id": "101945@1573836887", "videoPointerID": null, "mode": 1, "spinClockTiltHour": 11, "spinClockTiltMinute": 18, "horizontalAngle": "-3.2", "launchAngle": 3.2070477, "rifleSpin": 2257.31079, "pitch_id": 1573836887, "_day": 15, "_month": 11, "_year": 2019, "_hour": 16, "_minute": 54, "_second": 47, "_milisecond": 0, "speed": 70.7, "spin": 2265, "trueSpin": 186, "spinEfficiency": 8.2, "spinConfidence": 0.911238551, "releaseHeight": 3.1164291385952403, "releaseSide": 2.38271949181071, "releaseExtension": "-", "pitchType": 4, "horizontalBreak": -0.7, "verticalBreak": 0.6, "strike": "Y", "szx": -5.9, "szy": 15.4, "no": 5, "date": "15 NOV 19", "date_original": "2019-11-15T16:54:47.000Z", "truespin": 186, "selected": false, "spinAxis": "00h:42m", "gyroDegree": "85.3"}, {"_id": "101945@1573836839", "videoPointerID": null, "mode": 1, "spinClockTiltHour": 9, "spinClockTiltMinute": 44, "horizontalAngle": "-2.9", "launchAngle": 2.672112, "rifleSpin": 2072.42139, "pitch_id": 1573836839, "_day": 15, "_month": 11, "_year": 2019, "_hour": 16, "_minute": 53, "_second": 59, "_milisecond": 0, "speed": 72.1, "spin": 2136, "trueSpin": 517, "spinEfficiency": 24.2, "spinConfidence": 0.8601024, "releaseHeight": 3.054366303855235, "releaseSide": 2.51251575185052, "releaseExtension": "-", "pitchType": 4, "horizontalBreak": 4, "verticalBreak": 1, "strike": "N", "szx": -5.4, "szy": 11.1, "no": 6, "date": "15 NOV 19", "date_original": "2019-11-15T16:53:59.000Z", "truespin": 517, "selected": false, "spinAxis": "02h:16m", "gyroDegree": "76.0"}, {"_id": "101945@1573836820", "videoPointerID": null, "mode": 1, "spinClockTiltHour": 9, "spinClockTiltMinute": 38, "horizontalAngle": "-4.3", "launchAngle": 2.23955131, "rifleSpin": 2135.12256, "pitch_id": 1573836820, "_day": 15, "_month": 11, "_year": 2019, "_hour": 16, "_minute": 53, "_second": 40, "_milisecond": 0, "speed": 73.1, "spin": 2205, "trueSpin": 549, "spinEfficiency": 24.9, "spinConfidence": 0.876776457, "releaseHeight": 3.18907119907311, "releaseSide": 2.5609498070422503, "releaseExtension": "-", "pitchType": 4, "horizontalBreak": 4.6, "verticalBreak": 0.2, "strike": "N", "szx": -18.8, "szy": 8.7, "no": 7, "date": "15 NOV 19", "date_original": "2019-11-15T16:53:40.000Z", "truespin": 549, "selected": false, "spinAxis": "02h:22m", "gyroDegree": "75.6"}, {"_id": "101945@1573836601", "videoPointerID": null, "mode": 1, "spinClockTiltHour": 0, "spinClockTiltMinute": 2, "horizontalAngle": "-1.6", "launchAngle": 3.57987642, "rifleSpin": 2113.73755, "pitch_id": 1573836601, "_day": 15, "_month": 11, "_year": 2019, "_hour": 16, "_minute": 50, "_second": 1, "_milisecond": 0, "speed": 69.2, "spin": 2125, "trueSpin": 216, "spinEfficiency": 10.2, "spinConfidence": 0.8753956, "releaseHeight": 3.0097506607428, "releaseSide": 2.45618143417959, "releaseExtension": "-", "pitchType": 4, "horizontalBreak": -1.5, "verticalBreak": 1.8, "strike": "N", "szx": 14.1, "szy": 17.9, "no": 8, "date": "15 NOV 19", "date_original": "2019-11-15T16:50:01.000Z", "truespin": 216, "selected": false, "spinAxis": "11h:58m", "gyroDegree": "84.2"}, {"_id": "101945@1571245965", "videoPointerID": null, "mode": 1, "spinClockTiltHour": 9, "spinClockTiltMinute": 4, "horizontalAngle": "-4.4", "launchAngle": 3.000318, "rifleSpin": 1320.23486, "pitch_id": 1571245965, "_day": 16, "_month": 10, "_year": 2019, "_hour": 17, "_minute": 12, "_second": 45, "_milisecond": 0, "speed": 79.6, "spin": 2217, "trueSpin": 1782, "spinEfficiency": 80.3, "spinConfidence": 0.8390028, "releaseHeight": 3.821578778774679, "releaseSide": 2.370128054783697, "releaseExtension": "-", "pitchType": 4, "horizontalBreak": 16.7, "verticalBreak": -0.5, "strike": "Y", "szx": 1.8, "szy": 32.8, "no": 9, "date": "16 OCT 19", "date_original": "2019-10-16T17:12:45.000Z", "truespin": 1782, "selected": false, "spinAxis": "02h:56m", "gyroDegree": "36.5"}, {"_id": "101945@1571245946", "videoPointerID": null, "mode": 1, "spinClockTiltHour": 9, "spinClockTiltMinute": 6, "horizontalAngle": "-1.5", "launchAngle": 3.49180555, "rifleSpin": 1310.27368, "pitch_id": 1571245946, "_day": 16, "_month": 10, "_year": 2019, "_hour": 17, "_minute": 12, "_second": 26, "_milisecond": 0, "speed": 79.1, "spin": 2206, "trueSpin": 0, "spinEfficiency": 0, "spinConfidence": 0, "releaseHeight": 3.796508470337622, "releaseSide": 2.50530741850623, "releaseExtension": "-", "pitchType": 4, "horizontalBreak": 0, "verticalBreak": 0, "strike": "N", "szx": 32.1, "szy": 29.1, "no": 10, "date": "16 OCT 19", "date_original": "2019-10-16T17:12:26.000Z", "truespin": 0, "selected": false, "spinAxis": 0, "gyroDegree": "90.0"}, {"_id": "101945@1571245922", "videoPointerID": null, "mode": 1, "spinClockTiltHour": 9, "spinClockTiltMinute": 2, "horizontalAngle": "-3.7", "launchAngle": 2.99203467, "rifleSpin": 1618.484, "pitch_id": 1571245922, "_day": 16, "_month": 10, "_year": 2019, "_hour": 17, "_minute": 12, "_second": 2, "_milisecond": 0, "speed": 78.3, "spin": 2256, "trueSpin": 1571, "spinEfficiency": 69.7, "spinConfidence": 0.9436063, "releaseHeight": 3.7267471841423463, "releaseSide": 2.40989928187827, "releaseExtension": "-", "pitchType": 4, "horizontalBreak": 15.2, "verticalBreak": -0.8, "strike": "Y", "szx": 2.4, "szy": 33, "no": 11, "date": "16 OCT 19", "date_original": "2019-10-16T17:12:02.000Z", "truespin": 1571, "selected": false, "spinAxis": "02h:58m", "gyroDegree": "45.9"}, {"_id": "101945@1571245901", "videoPointerID": null, "mode": 1, "spinClockTiltHour": 9, "spinClockTiltMinute": 2, "horizontalAngle": "-1.0", "launchAngle": 2.66836953, "rifleSpin": 1350.82825, "pitch_id": 1571245901, "_day": 16, "_month": 10, "_year": 2019, "_hour": 17, "_minute": 11, "_second": 41, "_milisecond": 0, "speed": 79.2, "spin": 2128, "trueSpin": 0, "spinEfficiency": 0, "spinConfidence": 0, "releaseHeight": 3.7719481356546214, "releaseSide": 2.4200385371430255, "releaseExtension": "-", "pitchType": 4, "horizontalBreak": 0, "verticalBreak": 0, "strike": "N", "szx": 36, "szy": 21.8, "no": 12, "date": "16 OCT 19", "date_original": "2019-10-16T17:11:41.000Z", "truespin": 0, "selected": false, "spinAxis": 0, "gyroDegree": "90.0"}, {"_id": "101945@1571245885", "videoPointerID": null, "mode": 1, "spinClockTiltHour": 8, "spinClockTiltMinute": 54, "horizontalAngle": "-3.1", "launchAngle": 3.18106437, "rifleSpin": 1363.09607, "pitch_id": 1571245885, "_day": 16, "_month": 10, "_year": 2019, "_hour": 17, "_minute": 11, "_second": 25, "_milisecond": 0, "speed": 78.5, "spin": 2182, "trueSpin": 1704, "spinEfficiency": 78.1, "spinConfidence": 0.886788, "releaseHeight": 3.5602824201097922, "releaseSide": 2.41483858634772, "releaseExtension": "-", "pitchType": 4, "horizontalBreak": 16, "verticalBreak": -1.7, "strike": "Y", "szx": 10.4, "szy": 26.7, "no": 13, "date": "16 OCT 19", "date_original": "2019-10-16T17:11:25.000Z", "truespin": 1704, "selected": false, "spinAxis": "03h:06m", "gyroDegree": "38.7"}, {"_id": "101945@1571245862", "videoPointerID": null, "mode": 1, "spinClockTiltHour": 9, "spinClockTiltMinute": 2, "horizontalAngle": "-2.2", "launchAngle": 1.92109561, "rifleSpin": 1288.17859, "pitch_id": 1571245862, "_day": 16, "_month": 10, "_year": 2019, "_hour": 17, "_minute": 11, "_second": 2, "_milisecond": 0, "speed": 78.7, "spin": 2128, "trueSpin": 0, "spinEfficiency": 0, "spinConfidence": 0, "releaseHeight": 3.7636175910225362, "releaseSide": 2.446978153325706, "releaseExtension": "-", "pitchType": 4, "horizontalBreak": 0, "verticalBreak": 0, "strike": "N", "szx": 27.1, "szy": 10.7, "no": 14, "date": "16 OCT 19", "date_original": "2019-10-16T17:11:02.000Z", "truespin": 0, "selected": false, "spinAxis": 0, "gyroDegree": "90.0"}, {"_id": "101945@1571245636", "videoPointerID": null, "mode": 1, "spinClockTiltHour": 9, "spinClockTiltMinute": 36, "horizontalAngle": "-1.9", "launchAngle": 2.143003, "rifleSpin": 2167.69775, "pitch_id": 1571245636, "_day": 16, "_month": 10, "_year": 2019, "_hour": 17, "_minute": 7, "_second": 16, "_milisecond": 0, "speed": 72.2, "spin": 2313, "trueSpin": 808, "spinEfficiency": 34.9, "spinConfidence": 0.806555033, "releaseHeight": 3.4736132270646696, "releaseSide": 2.207245259260525, "releaseExtension": "-", "pitchType": 4, "horizontalBreak": 6.9, "verticalBreak": 1.8, "strike": "N", "szx": 3.8, "szy": 8.2, "no": 15, "date": "16 OCT 19", "date_original": "2019-10-16T17:07:16.000Z", "truespin": 808, "selected": false, "spinAxis": "02h:24m", "gyroDegree": "69.6"}, {"_id": "101945@1571245619", "videoPointerID": null, "mode": 1, "spinClockTiltHour": 8, "spinClockTiltMinute": 56, "horizontalAngle": "-4.2", "launchAngle": 2.62756515, "rifleSpin": 1318.26208, "pitch_id": 1571245619, "_day": 16, "_month": 10, "_year": 2019, "_hour": 17, "_minute": 6, "_second": 59, "_milisecond": 0, "speed": 78.5, "spin": 2141, "trueSpin": 1687, "spinEfficiency": 78.8, "spinConfidence": 0.8740926, "releaseHeight": 3.5908110290800805, "releaseSide": 2.38280741832003, "releaseExtension": "-", "pitchType": 0, "horizontalBreak": 16.4, "verticalBreak": -1.5, "strike": "Y", "szx": 1.4, "szy": 24.7, "no": 16, "date": "16 OCT 19", "date_original": "2019-10-16T17:06:59.000Z", "truespin": 1687, "selected": false, "spinAxis": "03h:04m", "gyroDegree": "38.0"}, {"_id": "101945@1571245594", "videoPointerID": null, "mode": 1, "spinClockTiltHour": 9, "spinClockTiltMinute": 30, "horizontalAngle": "-3.8", "launchAngle": 5.008755, "rifleSpin": 2113.8252, "pitch_id": 1571245594, "_day": 16, "_month": 10, "_year": 2019, "_hour": 17, "_minute": 6, "_second": 34, "_milisecond": 0, "speed": 71.2, "spin": 2239, "trueSpin": 738, "spinEfficiency": 33, "spinConfidence": 0.876835644, "releaseHeight": 3.3507513174291, "releaseSide": 2.32359514788882, "releaseExtension": "-", "pitchType": 4, "horizontalBreak": 5.3, "verticalBreak": 0.5, "strike": "N", "szx": -12.7, "szy": 38.7, "no": 17, "date": "16 OCT 19", "date_original": "2019-10-16T17:06:34.000Z", "truespin": 738, "selected": false, "spinAxis": "02h:30m", "gyroDegree": "70.8"}, {"_id": "101945@1571245564", "videoPointerID": null, "mode": 1, "spinClockTiltHour": 9, "spinClockTiltMinute": 2, "horizontalAngle": "-4.2", "launchAngle": 1.28207076, "rifleSpin": 1356.49817, "pitch_id": 1571245564, "_day": 16, "_month": 10, "_year": 2019, "_hour": 17, "_minute": 6, "_second": 4, "_milisecond": 0, "speed": 79.5, "spin": 2163, "trueSpin": 1684, "spinEfficiency": 77.9, "spinConfidence": 0.8612706, "releaseHeight": 3.760050694691655, "releaseSide": 2.3079934418283603, "releaseExtension": "-", "pitchType": 0, "horizontalBreak": 16.5, "verticalBreak": -0.7, "strike": "N", "szx": -0.2, "szy": 10.1, "no": 18, "date": "16 OCT 19", "date_original": "2019-10-16T17:06:04.000Z", "truespin": 1684, "selected": false, "spinAxis": "02h:58m", "gyroDegree": "38.9"}, {"_id": "101945@1571245541", "videoPointerID": null, "mode": 1, "spinClockTiltHour": 9, "spinClockTiltMinute": 2, "horizontalAngle": "-2.5", "launchAngle": 1.73079062, "rifleSpin": 1360.11377, "pitch_id": 1571245541, "_day": 16, "_month": 10, "_year": 2019, "_hour": 17, "_minute": 5, "_second": 41, "_milisecond": 0, "speed": 78.6, "spin": 2184, "trueSpin": 0, "spinEfficiency": 0, "spinConfidence": 0, "releaseHeight": 3.867976154173287, "releaseSide": 2.40225525299526, "releaseExtension": "-", "pitchType": 0, "horizontalBreak": 0, "verticalBreak": 0, "strike": "N", "szx": 25.4, "szy": 22.6, "no": 19, "date": "16 OCT 19", "date_original": "2019-10-16T17:05:41.000Z", "truespin": 0, "selected": false, "spinAxis": 0, "gyroDegree": "90.0"}, {"_id": "101945@1571245519", "videoPointerID": null, "mode": 1, "spinClockTiltHour": 9, "spinClockTiltMinute": 26, "horizontalAngle": "0.1", "launchAngle": 3.35775423, "rifleSpin": 1367.63989, "pitch_id": 1571245519, "_day": 16, "_month": 10, "_year": 2019, "_hour": 17, "_minute": 5, "_second": 19, "_milisecond": 0, "speed": 80.1, "spin": 2294, "trueSpin": 0, "spinEfficiency": 0, "spinConfidence": 0, "releaseHeight": 3.9648724141630893, "releaseSide": 2.48836647359859, "releaseExtension": "-", "pitchType": 0, "horizontalBreak": 0, "verticalBreak": 0, "strike": "N", "szx": 47, "szy": 36.6, "no": 20, "date": "16 OCT 19", "date_original": "2019-10-16T17:05:19.000Z", "truespin": 0, "selected": false, "spinAxis": 0, "gyroDegree": "90.0"}, {"_id": "101945@1571245465", "videoPointerID": null, "mode": 1, "spinClockTiltHour": 8, "spinClockTiltMinute": 30, "horizontalAngle": "-5.2", "launchAngle": 3.327453, "rifleSpin": 1287.26953, "pitch_id": 1571245465, "_day": 16, "_month": 10, "_year": 2019, "_hour": 17, "_minute": 4, "_second": 25, "_milisecond": 0, "speed": 77.5, "spin": 2091, "trueSpin": 1648, "spinEfficiency": 78.8, "spinConfidence": 0.905566931, "releaseHeight": 3.657900694536387, "releaseSide": 2.2957693604449503, "releaseExtension": "-", "pitchType": 0, "horizontalBreak": 15.2, "verticalBreak": -5.5, "strike": "N", "szx": -12.7, "szy": 30.6, "no": 21, "date": "16 OCT 19", "date_original": "2019-10-16T17:04:25.000Z", "truespin": 1648, "selected": false, "spinAxis": "03h:30m", "gyroDegree": "38.0"}, {"_id": "101945@1571245443", "videoPointerID": null, "mode": 1, "spinClockTiltHour": 9, "spinClockTiltMinute": 18, "horizontalAngle": "-4.8", "launchAngle": 2.322352, "rifleSpin": 2119.22559, "pitch_id": 1571245443, "_day": 16, "_month": 10, "_year": 2019, "_hour": 17, "_minute": 4, "_second": 3, "_milisecond": 0, "speed": 72.6, "spin": 2262, "trueSpin": 790, "spinEfficiency": 34.9, "spinConfidence": 0.919268847, "releaseHeight": 3.4605932795383167, "releaseSide": 2.3384538946305655, "releaseExtension": "-", "pitchType": 4, "horizontalBreak": 6.9, "verticalBreak": -0.5, "strike": "N", "szx": -19.9, "szy": 11.6, "no": 22, "date": "16 OCT 19", "date_original": "2019-10-16T17:04:03.000Z", "truespin": 790, "selected": false, "spinAxis": "02h:42m", "gyroDegree": "69.6"}, {"_id": "101945@1571245422", "videoPointerID": null, "mode": 1, "spinClockTiltHour": 9, "spinClockTiltMinute": 26, "horizontalAngle": "-2.5", "launchAngle": 6.17626953, "rifleSpin": 2185.01929, "pitch_id": 1571245422, "_day": 16, "_month": 10, "_year": 2019, "_hour": 17, "_minute": 3, "_second": 42, "_milisecond": 0, "speed": 73.6, "spin": 2316, "trueSpin": 0, "spinEfficiency": 0, "spinConfidence": 0, "releaseHeight": 2.66642585707134, "releaseSide": 2.509211427698516, "releaseExtension": "-", "pitchType": 4, "horizontalBreak": 0, "verticalBreak": 0, "strike": "N", "szx": -2.2, "szy": 6.2, "no": 23, "date": "16 OCT 19", "date_original": "2019-10-16T17:03:42.000Z", "truespin": 0, "selected": false, "spinAxis": 0, "gyroDegree": "90.0"}, {"_id": "101945@1571245404", "videoPointerID": null, "mode": 1, "spinClockTiltHour": 9, "spinClockTiltMinute": 32, "horizontalAngle": "-3.9", "launchAngle": 2.00764775, "rifleSpin": 2212.26538, "pitch_id": 1571245404, "_day": 16, "_month": 10, "_year": 2019, "_hour": 17, "_minute": 3, "_second": 24, "_milisecond": 0, "speed": 73.3, "spin": 2298, "trueSpin": 622, "spinEfficiency": 27, "spinConfidence": 0.811497331, "releaseHeight": 3.4608572559166713, "releaseSide": 2.366799737849504, "releaseExtension": "-", "pitchType": 4, "horizontalBreak": 5.2, "verticalBreak": 0.2, "strike": "N", "szx": -14.2, "szy": 3.7, "no": 24, "date": "16 OCT 19", "date_original": "2019-10-16T17:03:24.000Z", "truespin": 622, "selected": false, "spinAxis": "02h:28m", "gyroDegree": "74.3"}, {"_id": "101945@1571245387", "videoPointerID": null, "mode": 1, "spinClockTiltHour": 12, "spinClockTiltMinute": 0, "horizontalAngle": "-", "launchAngle": 0, "rifleSpin": 0, "pitch_id": 1571245387, "_day": 16, "_month": 10, "_year": 2019, "_hour": 17, "_minute": 3, "_second": 7, "_milisecond": 0, "speed": 0, "spin": 0, "trueSpin": 0, "spinEfficiency": 0, "spinConfidence": 0, "releaseHeight": 0, "releaseSide": 0, "releaseExtension": "-", "pitchType": 0, "horizontalBreak": 0, "verticalBreak": 0, "strike": "N", "szx": 0, "szy": 0, "no": 25, "date": "16 OCT 19", "date_original": "2019-10-16T17:03:07.000Z", "truespin": 0, "selected": false, "spinAxis": 0, "gyroDegree": "-"}, {"_id": "101945@1571245294", "videoPointerID": null, "mode": 1, "spinClockTiltHour": 9, "spinClockTiltMinute": 28, "horizontalAngle": "-3.5", "launchAngle": 3.2587, "rifleSpin": 2065.29028, "pitch_id": 1571245294, "_day": 16, "_month": 10, "_year": 2019, "_hour": 17, "_minute": 1, "_second": 34, "_milisecond": 0, "speed": 72.2, "spin": 2214, "trueSpin": 797, "spinEfficiency": 36, "spinConfidence": 0.9032938, "releaseHeight": 3.604182190517727, "releaseSide": 2.37787828445427, "releaseExtension": "-", "pitchType": 4, "horizontalBreak": 6.8, "verticalBreak": 0.7, "strike": "Y", "szx": -3.3, "szy": 23, "no": 26, "date": "16 OCT 19", "date_original": "2019-10-16T17:01:34.000Z", "truespin": 797, "selected": false, "spinAxis": "02h:32m", "gyroDegree": "68.9"}, {"_id": "101945@1571245275", "videoPointerID": null, "mode": 1, "spinClockTiltHour": 9, "spinClockTiltMinute": 22, "horizontalAngle": "-2.6", "launchAngle": 3.49839973, "rifleSpin": 2076.57031, "pitch_id": 1571245275, "_day": 16, "_month": 10, "_year": 2019, "_hour": 17, "_minute": 1, "_second": 15, "_milisecond": 0, "speed": 74.5, "spin": 2230, "trueSpin": 814, "spinEfficiency": 36.5, "spinConfidence": 0.8577019, "releaseHeight": 3.6451768100026114, "releaseSide": 2.442163825890567, "releaseExtension": "-", "pitchType": 4, "horizontalBreak": 6.8, "verticalBreak": 0.6, "strike": "Y", "szx": 1, "szy": 31.2, "no": 27, "date": "16 OCT 19", "date_original": "2019-10-16T17:01:15.000Z", "truespin": 814, "selected": false, "spinAxis": "02h:38m", "gyroDegree": "68.6"}, {"_id": "101945@1571245251", "videoPointerID": null, "mode": 1, "spinClockTiltHour": 9, "spinClockTiltMinute": 12, "horizontalAngle": "-6.4", "launchAngle": 1.94294894, "rifleSpin": 1936.45813, "pitch_id": 1571245251, "_day": 16, "_month": 10, "_year": 2019, "_hour": 17, "_minute": 0, "_second": 51, "_milisecond": 0, "speed": 73.6, "spin": 2219, "trueSpin": 0, "spinEfficiency": 0, "spinConfidence": 0, "releaseHeight": 3.6629986932318, "releaseSide": 2.4191217228371698, "releaseExtension": "-", "pitchType": 4, "horizontalBreak": 0, "verticalBreak": 0, "strike": "N", "szx": -37.6, "szy": 9.5, "no": 28, "date": "16 OCT 19", "date_original": "2019-10-16T17:00:51.000Z", "truespin": 0, "selected": false, "spinAxis": 0, "gyroDegree": "90.0"}, {"_id": "101945@1571245224", "videoPointerID": null, "mode": 1, "spinClockTiltHour": 9, "spinClockTiltMinute": 0, "horizontalAngle": "-5.4", "launchAngle": 2.29940772, "rifleSpin": 1263.78162, "pitch_id": 1571245224, "_day": 16, "_month": 10, "_year": 2019, "_hour": 17, "_minute": 0, "_second": 24, "_milisecond": 0, "speed": 79.5, "spin": 2071, "trueSpin": 0, "spinEfficiency": 0, "spinConfidence": 0, "releaseHeight": 3.9919460034430863, "releaseSide": 2.38335433433136, "releaseExtension": "-", "pitchType": 0, "horizontalBreak": 0, "verticalBreak": 0, "strike": "Y", "szx": -8.1, "szy": 17.5, "no": 29, "date": "16 OCT 19", "date_original": "2019-10-16T17:00:24.000Z", "truespin": 0, "selected": false, "spinAxis": 0, "gyroDegree": "90.0"}, {"_id": "101945@1571245206", "videoPointerID": null, "mode": 1, "spinClockTiltHour": 9, "spinClockTiltMinute": 2, "horizontalAngle": "-0.0", "launchAngle": 2.27415562, "rifleSpin": 1349.19214, "pitch_id": 1571245206, "_day": 16, "_month": 10, "_year": 2019, "_hour": 17, "_minute": 0, "_second": 6, "_milisecond": 0, "speed": 78.6, "spin": 2130, "trueSpin": 0, "spinEfficiency": 0, "spinConfidence": 0, "releaseHeight": 3.657832617108462, "releaseSide": 2.1815096653893855, "releaseExtension": "-", "pitchType": 5, "horizontalBreak": 0, "verticalBreak": 0, "strike": "N", "szx": 31.7, "szy": 11.8, "no": 30, "date": "16 OCT 19", "date_original": "2019-10-16T17:00:06.000Z", "truespin": 0, "selected": false, "spinAxis": 0, "gyroDegree": "90.0"}, {"_id": "101945@1571245188", "videoPointerID": null, "mode": 1, "spinClockTiltHour": 9, "spinClockTiltMinute": 10, "horizontalAngle": "-2.6", "launchAngle": 1.85406232, "rifleSpin": 1547.06042, "pitch_id": 1571245188, "_day": 16, "_month": 10, "_year": 2019, "_hour": 16, "_minute": 59, "_second": 48, "_milisecond": 0, "speed": 76.5, "spin": 2127, "trueSpin": 0, "spinEfficiency": 0, "spinConfidence": 0, "releaseHeight": 3.776750924375832, "releaseSide": 2.5761692952543602, "releaseExtension": "-", "pitchType": 5, "horizontalBreak": 0, "verticalBreak": 0, "strike": "N", "szx": 22.8, "szy": 15.2, "no": 31, "date": "16 OCT 19", "date_original": "2019-10-16T16:59:48.000Z", "truespin": 0, "selected": false, "spinAxis": 0, "gyroDegree": "90.0"}, {"_id": "101945@1571245173", "videoPointerID": null, "mode": 1, "spinClockTiltHour": 9, "spinClockTiltMinute": 4, "horizontalAngle": "-2.8", "launchAngle": 2.16042638, "rifleSpin": 1318.604, "pitch_id": 1571245173, "_day": 16, "_month": 10, "_year": 2019, "_hour": 16, "_minute": 59, "_second": 33, "_milisecond": 0, "speed": 78.9, "spin": 2140, "trueSpin": 1685, "spinEfficiency": 78.8, "spinConfidence": 0.8554539, "releaseHeight": 3.757221429595491, "releaseSide": 2.3356891636552346, "releaseExtension": "-", "pitchType": 0, "horizontalBreak": 16.6, "verticalBreak": -0.3, "strike": "N", "szx": 14.9, "szy": 16.9, "no": 32, "date": "16 OCT 19", "date_original": "2019-10-16T16:59:33.000Z", "truespin": 1685, "selected": false, "spinAxis": "02h:56m", "gyroDegree": "38.0"}, {"_id": "101945@1571245155", "videoPointerID": null, "mode": 1, "spinClockTiltHour": 8, "spinClockTiltMinute": 52, "horizontalAngle": "-2.1", "launchAngle": 3.607799, "rifleSpin": 1262.72937, "pitch_id": 1571245155, "_day": 16, "_month": 10, "_year": 2019, "_hour": 16, "_minute": 59, "_second": 15, "_milisecond": 0, "speed": 78.2, "spin": 2070, "trueSpin": 0, "spinEfficiency": 0, "spinConfidence": 0, "releaseHeight": 3.6268057469825608, "releaseSide": 2.491958540533184, "releaseExtension": "-", "pitchType": 0, "horizontalBreak": 0, "verticalBreak": 0, "strike": "N", "szx": 26.4, "szy": 32.7, "no": 33, "date": "16 OCT 19", "date_original": "2019-10-16T16:59:15.000Z", "truespin": 0, "selected": false, "spinAxis": 0, "gyroDegree": "90.0"}, {"_id": "101945@1571245135", "videoPointerID": null, "mode": 1, "spinClockTiltHour": 9, "spinClockTiltMinute": 0, "horizontalAngle": "-4.5", "launchAngle": 3.10303879, "rifleSpin": 1224.35022, "pitch_id": 1571245135, "_day": 16, "_month": 10, "_year": 2019, "_hour": 16, "_minute": 58, "_second": 55, "_milisecond": 0, "speed": 79.7, "spin": 2081, "trueSpin": 1682, "spinEfficiency": 80.9, "spinConfidence": 0.8714326, "releaseHeight": 3.873680058381432, "releaseSide": 2.45079856015566, "releaseExtension": "-", "pitchType": 0, "horizontalBreak": 16.4, "verticalBreak": -1, "strike": "Y", "szx": -1.1, "szy": 32.8, "no": 34, "date": "16 OCT 19", "date_original": "2019-10-16T16:58:55.000Z", "truespin": 1682, "selected": false, "spinAxis": "03h:00m", "gyroDegree": "36.1"}, {"_id": "101945@1571245117", "videoPointerID": null, "mode": 1, "spinClockTiltHour": 8, "spinClockTiltMinute": 56, "horizontalAngle": "-3.5", "launchAngle": 1.52530015, "rifleSpin": 976.9798, "pitch_id": 1571245117, "_day": 16, "_month": 10, "_year": 2019, "_hour": 16, "_minute": 58, "_second": 37, "_milisecond": 0, "speed": 78.5, "spin": 2017, "trueSpin": 1765, "spinEfficiency": 87.5, "spinConfidence": 0.8993474, "releaseHeight": 3.744308240599485, "releaseSide": 2.4995037702034453, "releaseExtension": "-", "pitchType": 0, "horizontalBreak": 18, "verticalBreak": -1.4, "strike": "N", "szx": 10.5, "szy": 11.9, "no": 35, "date": "16 OCT 19", "date_original": "2019-10-16T16:58:37.000Z", "truespin": 1765, "selected": false, "spinAxis": "03h:04m", "gyroDegree": "29.0"}, {"_id": "101945@1571245099", "videoPointerID": null, "mode": 1, "spinClockTiltHour": 9, "spinClockTiltMinute": 4, "horizontalAngle": "-4.4", "launchAngle": 2.594257, "rifleSpin": 1243.55127, "pitch_id": 1571245099, "_day": 16, "_month": 10, "_year": 2019, "_hour": 16, "_minute": 58, "_second": 19, "_milisecond": 0, "speed": 78.1, "spin": 2069, "trueSpin": 1654, "spinEfficiency": 79.9, "spinConfidence": 0.8889154, "releaseHeight": 3.881914015086861, "releaseSide": 2.3735921952089103, "releaseExtension": "-", "pitchType": 0, "horizontalBreak": 16.5, "verticalBreak": -0.5, "strike": "Y", "szx": -1.5, "szy": 28.1, "no": 36, "date": "16 OCT 19", "date_original": "2019-10-16T16:58:19.000Z", "truespin": 1654, "selected": false, "spinAxis": "02h:56m", "gyroDegree": "36.9"}, {"_id": "101945@1571245079", "videoPointerID": null, "mode": 1, "spinClockTiltHour": 8, "spinClockTiltMinute": 36, "horizontalAngle": "-4.3", "launchAngle": 2.554584, "rifleSpin": 835.49884, "pitch_id": 1571245079, "_day": 16, "_month": 10, "_year": 2019, "_hour": 16, "_minute": 57, "_second": 59, "_milisecond": 0, "speed": 77.4, "spin": 1859, "trueSpin": 1661, "spinEfficiency": 89.3, "spinConfidence": 0.8296693, "releaseHeight": 3.7422255962393645, "releaseSide": 2.60156890159218, "releaseExtension": "-", "pitchType": 0, "horizontalBreak": 17.4, "verticalBreak": -4.6, "strike": "Y", "szx": 4.9, "szy": 16.5, "no": 37, "date": "16 OCT 19", "date_original": "2019-10-16T16:57:59.000Z", "truespin": 1661, "selected": false, "spinAxis": "03h:24m", "gyroDegree": "26.7"}, {"_id": "101945@1571245063", "videoPointerID": null, "mode": 1, "spinClockTiltHour": 9, "spinClockTiltMinute": 4, "horizontalAngle": "-3.0", "launchAngle": 4.15422153, "rifleSpin": 1213.99158, "pitch_id": 1571245063, "_day": 16, "_month": 10, "_year": 2019, "_hour": 16, "_minute": 57, "_second": 43, "_milisecond": 0, "speed": 77.6, "spin": 2060, "trueSpin": 0, "spinEfficiency": 0, "spinConfidence": 0, "releaseHeight": 3.969881338055217, "releaseSide": 2.52311844215535, "releaseExtension": "-", "pitchType": 0, "horizontalBreak": 0, "verticalBreak": 0, "strike": "N", "szx": 17.9, "szy": 41.3, "no": 38, "date": "16 OCT 19", "date_original": "2019-10-16T16:57:43.000Z", "truespin": 0, "selected": false, "spinAxis": 0, "gyroDegree": "90.0"}, {"_id": "101945@1569961216", "videoPointerID": null, "mode": 1, "spinClockTiltHour": 9, "spinClockTiltMinute": 10, "horizontalAngle": "-5.1", "launchAngle": 2.04749274, "rifleSpin": 1276.04407, "pitch_id": 1569961216, "_day": 1, "_month": 10, "_year": 2019, "_hour": 20, "_minute": 20, "_second": 16, "_milisecond": 0, "speed": 79.8, "spin": 2127, "trueSpin": 1702, "spinEfficiency": 80, "spinConfidence": 0.802460432, "releaseHeight": 3.7889409506410803, "releaseSide": 2.88474344270502, "releaseExtension": "-", "pitchType": 0, "horizontalBreak": 16.8, "verticalBreak": 0.4, "strike": "Y", "szx": 0.1, "szy": 20.3, "no": 39, "date": "1 OCT 19", "date_original": "2019-10-01T20:20:16.000Z", "truespin": 1702, "selected": false, "spinAxis": "02h:50m", "gyroDegree": "36.9"}, {"_id": "101945@1569961187", "videoPointerID": null, "mode": 1, "spinClockTiltHour": 5, "spinClockTiltMinute": 50, "horizontalAngle": "-4.7", "launchAngle": 2.73688912, "rifleSpin": -138.062851, "pitch_id": 1569961187, "_day": 1, "_month": 10, "_year": 2019, "_hour": 20, "_minute": 19, "_second": 47, "_milisecond": 0, "speed": 77.5, "spin": 994, "trueSpin": 0, "spinEfficiency": 0, "spinConfidence": 0, "releaseHeight": 3.4836843884973003, "releaseSide": 3.12227428296108, "releaseExtension": "-", "pitchType": 0, "horizontalBreak": 0, "verticalBreak": 0, "strike": "Y", "szx": 1.1, "szy": 21.7, "no": 40, "date": "1 OCT 19", "date_original": "2019-10-01T20:19:47.000Z", "truespin": 0, "selected": false, "spinAxis": 0, "gyroDegree": "-90.0"}, {"_id": "101945@1569961147", "videoPointerID": null, "mode": 1, "spinClockTiltHour": 12, "spinClockTiltMinute": 0, "horizontalAngle": "-", "launchAngle": 0, "rifleSpin": 0, "pitch_id": 1569961147, "_day": 1, "_month": 10, "_year": 2019, "_hour": 20, "_minute": 19, "_second": 7, "_milisecond": 0, "speed": 0, "spin": 0, "trueSpin": 0, "spinEfficiency": 0, "spinConfidence": 0, "releaseHeight": 0, "releaseSide": 0, "releaseExtension": "-", "pitchType": 4, "horizontalBreak": 0, "verticalBreak": 0, "strike": "N", "szx": 0, "szy": 0, "no": 41, "date": "1 OCT 19", "date_original": "2019-10-01T20:19:07.000Z", "truespin": 0, "selected": false, "spinAxis": 0, "gyroDegree": "-"}, {"_id": "101945@1569961117", "videoPointerID": null, "mode": 1, "spinClockTiltHour": 9, "spinClockTiltMinute": 46, "horizontalAngle": "-5.1", "launchAngle": 3.299171, "rifleSpin": 2224.53345, "pitch_id": 1569961117, "_day": 1, "_month": 10, "_year": 2019, "_hour": 20, "_minute": 18, "_second": 37, "_milisecond": 0, "speed": 73.2, "spin": 2353, "trueSpin": 767, "spinEfficiency": 32.6, "spinConfidence": 0.8457837, "releaseHeight": 3.3432283515384, "releaseSide": 2.9252883902732103, "releaseExtension": "-", "pitchType": 4, "horizontalBreak": 5.7, "verticalBreak": 1, "strike": "N", "szx": -19.1, "szy": 19.5, "no": 42, "date": "1 OCT 19", "date_original": "2019-10-01T20:18:37.000Z", "truespin": 767, "selected": false, "spinAxis": "02h:14m", "gyroDegree": "71.0"}, {"_id": "101945@1569961097", "videoPointerID": null, "mode": 1, "spinClockTiltHour": 9, "spinClockTiltMinute": 46, "horizontalAngle": "-4.8", "launchAngle": 3.76062536, "rifleSpin": 2272.248, "pitch_id": 1569961097, "_day": 1, "_month": 10, "_year": 2019, "_hour": 20, "_minute": 18, "_second": 17, "_milisecond": 0, "speed": 71.7, "spin": 2298, "trueSpin": 340, "spinEfficiency": 14.8, "spinConfidence": 0.8362767, "releaseHeight": 3.4135541062384713, "releaseSide": 3.0918437022061642, "releaseExtension": "-", "pitchType": 4, "horizontalBreak": 1.7, "verticalBreak": -0.6, "strike": "N", "szx": -12.2, "szy": 34.9, "no": 43, "date": "1 OCT 19", "date_original": "2019-10-01T20:18:17.000Z", "truespin": 340, "selected": false, "spinAxis": "02h:14m", "gyroDegree": "81.5"}, {"_id": "101945@1569961081", "videoPointerID": null, "mode": 1, "spinClockTiltHour": 10, "spinClockTiltMinute": 6, "horizontalAngle": "-6.7", "launchAngle": 3.14582968, "rifleSpin": 2320.87964, "pitch_id": 1569961081, "_day": 1, "_month": 10, "_year": 2019, "_hour": 20, "_minute": 18, "_second": 1, "_milisecond": 0, "speed": 72.8, "spin": 2339, "trueSpin": 0, "spinEfficiency": 0, "spinConfidence": 0, "releaseHeight": 3.5572342573755, "releaseSide": 2.966276779443124, "releaseExtension": "-", "pitchType": 4, "horizontalBreak": 0, "verticalBreak": 0, "strike": "N", "szx": -39.7, "szy": 30.8, "no": 44, "date": "1 OCT 19", "date_original": "2019-10-01T20:18:01.000Z", "truespin": 0, "selected": false, "spinAxis": 0, "gyroDegree": "90.0"}, {"_id": "101945@1569960983", "videoPointerID": null, "mode": 1, "spinClockTiltHour": 9, "spinClockTiltMinute": 24, "horizontalAngle": "-4.2", "launchAngle": 3.19289565, "rifleSpin": 2199.34937, "pitch_id": 1569960983, "_day": 1, "_month": 10, "_year": 2019, "_hour": 20, "_minute": 16, "_second": 23, "_milisecond": 0, "speed": 75.5, "spin": 2333, "trueSpin": 777, "spinEfficiency": 33.3, "spinConfidence": 0.773776531, "releaseHeight": 3.809238588467208, "releaseSide": 2.979968636419316, "releaseExtension": "-", "pitchType": 4, "horizontalBreak": 6.3, "verticalBreak": 0, "strike": "N", "szx": -3.9, "szy": 46.7, "no": 45, "date": "1 OCT 19", "date_original": "2019-10-01T20:16:23.000Z", "truespin": 777, "selected": false, "spinAxis": "02h:36m", "gyroDegree": "70.5"}, {"_id": "101945@1569960954", "videoPointerID": null, "mode": 1, "spinClockTiltHour": 1, "spinClockTiltMinute": 16, "horizontalAngle": "-2.1", "launchAngle": 2.87322521, "rifleSpin": 814.7686, "pitch_id": 1569960954, "_day": 1, "_month": 10, "_year": 2019, "_hour": 20, "_minute": 15, "_second": 54, "_milisecond": 0, "speed": 76.5, "spin": 1170, "trueSpin": 0, "spinEfficiency": 0, "spinConfidence": 0, "releaseHeight": 3.417959519630994, "releaseSide": 2.92043799656505, "releaseExtension": "-", "pitchType": 4, "horizontalBreak": 0, "verticalBreak": 0, "strike": "N", "szx": 7.9, "szy": 1.3, "no": 46, "date": "1 OCT 19", "date_original": "2019-10-01T20:15:54.000Z", "truespin": 0, "selected": false, "spinAxis": 0, "gyroDegree": "90.0"}, {"_id": "101945@1569960893", "videoPointerID": null, "mode": 1, "spinClockTiltHour": 2, "spinClockTiltMinute": 24, "horizontalAngle": "-3.5", "launchAngle": 2.44863582, "rifleSpin": 748.007446, "pitch_id": 1569960893, "_day": 1, "_month": 10, "_year": 2019, "_hour": 20, "_minute": 14, "_second": 53, "_milisecond": 0, "speed": 74.6, "spin": 1973, "trueSpin": 0, "spinEfficiency": 0, "spinConfidence": 0, "releaseHeight": 3.6947656224139447, "releaseSide": 2.86364993873595, "releaseExtension": "-", "pitchType": 4, "horizontalBreak": 0, "verticalBreak": 0, "strike": "Y", "szx": -0.4, "szy": 24, "no": 47, "date": "1 OCT 19", "date_original": "2019-10-01T20:14:53.000Z", "truespin": 0, "selected": false, "spinAxis": 0, "gyroDegree": "90.0"}, {"_id": "101945@1569960876", "videoPointerID": null, "mode": 1, "spinClockTiltHour": 9, "spinClockTiltMinute": 54, "horizontalAngle": "-4.8", "launchAngle": 1.53986371, "rifleSpin": 2208.201, "pitch_id": 1569960876, "_day": 1, "_month": 10, "_year": 2019, "_hour": 20, "_minute": 14, "_second": 36, "_milisecond": 0, "speed": 73.5, "spin": 2305, "trueSpin": 0, "spinEfficiency": 0, "spinConfidence": 0, "releaseHeight": 3.78889206612657, "releaseSide": 3.21094455868641, "releaseExtension": "-", "pitchType": 4, "horizontalBreak": 0, "verticalBreak": 0, "strike": "Y", "szx": -2.6, "szy": 24.8, "no": 48, "date": "1 OCT 19", "date_original": "2019-10-01T20:14:36.000Z", "truespin": 0, "selected": false, "spinAxis": 0, "gyroDegree": "90.0"}, {"_id": "101945@1569960858", "videoPointerID": null, "mode": 1, "spinClockTiltHour": 9, "spinClockTiltMinute": 0, "horizontalAngle": "-4.2", "launchAngle": 2.48428583, "rifleSpin": 1783.48071, "pitch_id": 1569960858, "_day": 1, "_month": 10, "_year": 2019, "_hour": 20, "_minute": 14, "_second": 18, "_milisecond": 0, "speed": 78.1, "spin": 2295, "trueSpin": 1444, "spinEfficiency": 62.9, "spinConfidence": 0.825285137, "releaseHeight": 3.896133109596663, "releaseSide": 3.01386450589341, "releaseExtension": "-", "pitchType": 5, "horizontalBreak": 13.4, "verticalBreak": -1.4, "strike": "Y", "szx": 7.9, "szy": 30.4, "no": 49, "date": "1 OCT 19", "date_original": "2019-10-01T20:14:18.000Z", "truespin": 1444, "selected": false, "spinAxis": "03h:00m", "gyroDegree": "51.0"}, {"_id": "101945@1569960838", "videoPointerID": null, "mode": 1, "spinClockTiltHour": 9, "spinClockTiltMinute": 2, "horizontalAngle": "-3.9", "launchAngle": 1.67967832, "rifleSpin": 1327.62646, "pitch_id": 1569960838, "_day": 1, "_month": 10, "_year": 2019, "_hour": 20, "_minute": 13, "_second": 58, "_milisecond": 0, "speed": 77.3, "spin": 2043, "trueSpin": 1553, "spinEfficiency": 76, "spinConfidence": 0.8736869, "releaseHeight": 3.797048988711147, "releaseSide": 2.846384420337003, "releaseExtension": "-", "pitchType": 5, "horizontalBreak": 15.8, "verticalBreak": -0.9, "strike": "N", "szx": 7.5, "szy": 11.8, "no": 50, "date": "1 OCT 19", "date_original": "2019-10-01T20:13:58.000Z", "truespin": 1553, "selected": false, "spinAxis": "02h:58m", "gyroDegree": "40.5"}, {"_id": "101945@1569960815", "videoPointerID": null, "mode": 1, "spinClockTiltHour": 1, "spinClockTiltMinute": 22, "horizontalAngle": "-3.9", "launchAngle": 1.12134564, "rifleSpin": 461.8149, "pitch_id": 1569960815, "_day": 1, "_month": 10, "_year": 2019, "_hour": 20, "_minute": 13, "_second": 35, "_milisecond": 0, "speed": 79.9, "spin": 836, "trueSpin": 0, "spinEfficiency": 0, "spinConfidence": 0, "releaseHeight": 4.0804429195881005, "releaseSide": 3.1111626064350038, "releaseExtension": "-", "pitchType": 5, "horizontalBreak": 0, "verticalBreak": 0, "strike": "N", "szx": 22.3, "szy": 19.3, "no": 51, "date": "1 OCT 19", "date_original": "2019-10-01T20:13:35.000Z", "truespin": 0, "selected": false, "spinAxis": 0, "gyroDegree": "90.0"}, {"_id": "101945@1569960783", "videoPointerID": null, "mode": 1, "spinClockTiltHour": 8, "spinClockTiltMinute": 46, "horizontalAngle": "-4.3", "launchAngle": 3.62845039, "rifleSpin": 1573.81677, "pitch_id": 1569960783, "_day": 1, "_month": 10, "_year": 2019, "_hour": 20, "_minute": 13, "_second": 3, "_milisecond": 0, "speed": 77.5, "spin": 2170, "trueSpin": 1494, "spinEfficiency": 68.9, "spinConfidence": 0.8121128, "releaseHeight": 3.8331731357476833, "releaseSide": 2.92535860024707, "releaseExtension": "-", "pitchType": 5, "horizontalBreak": 14, "verticalBreak": -3.1, "strike": "Y", "szx": 7.4, "szy": 33.8, "no": 52, "date": "1 OCT 19", "date_original": "2019-10-01T20:13:03.000Z", "truespin": 1494, "selected": false, "spinAxis": "03h:14m", "gyroDegree": "46.5"}, {"_id": "101945@1569960730", "videoPointerID": null, "mode": 1, "spinClockTiltHour": 8, "spinClockTiltMinute": 54, "horizontalAngle": "-5.4", "launchAngle": 2.05078888, "rifleSpin": 1380.49731, "pitch_id": 1569960730, "_day": 1, "_month": 10, "_year": 2019, "_hour": 20, "_minute": 12, "_second": 10, "_milisecond": 0, "speed": 79.8, "spin": 2185, "trueSpin": 1694, "spinEfficiency": 77.5, "spinConfidence": 0.878895164, "releaseHeight": 3.8037717249418384, "releaseSide": 3.136728853193025, "releaseExtension": "-", "pitchType": 5, "horizontalBreak": 16.3, "verticalBreak": -2.1, "strike": "Y", "szx": -3.9, "szy": 21.1, "no": 53, "date": "1 OCT 19", "date_original": "2019-10-01T20:12:10.000Z", "truespin": 1694, "selected": false, "spinAxis": "03h:06m", "gyroDegree": "39.2"}, {"_id": "101945@1569960701", "videoPointerID": null, "mode": 1, "spinClockTiltHour": 9, "spinClockTiltMinute": 4, "horizontalAngle": "-4.7", "launchAngle": 1.6989795, "rifleSpin": 1305.86121, "pitch_id": 1569960701, "_day": 1, "_month": 10, "_year": 2019, "_hour": 20, "_minute": 11, "_second": 41, "_milisecond": 0, "speed": 79.3, "spin": 2196, "trueSpin": 1765, "spinEfficiency": 80.4, "spinConfidence": 0.8380883, "releaseHeight": 3.869559749976219, "releaseSide": 2.8629255292860303, "releaseExtension": "-", "pitchType": 5, "horizontalBreak": 17.3, "verticalBreak": -0.6, "strike": "N", "szx": -4.7, "szy": 12.5, "no": 54, "date": "1 OCT 19", "date_original": "2019-10-01T20:11:41.000Z", "truespin": 1765, "selected": false, "spinAxis": "02h:56m", "gyroDegree": "36.5"}, {"_id": "101945@1569960671", "videoPointerID": null, "mode": 1, "spinClockTiltHour": 6, "spinClockTiltMinute": 54, "horizontalAngle": "-2.0", "launchAngle": 3.54988885, "rifleSpin": 1601.43787, "pitch_id": 1569960671, "_day": 1, "_month": 10, "_year": 2019, "_hour": 20, "_minute": 11, "_second": 11, "_milisecond": 0, "speed": 79.5, "spin": 1942, "trueSpin": 0, "spinEfficiency": 0, "spinConfidence": 0, "releaseHeight": 3.5078240866967225, "releaseSide": 2.76797769449604, "releaseExtension": "-", "pitchType": 5, "horizontalBreak": 0, "verticalBreak": 0, "strike": "N", "szx": 12.2, "szy": 5.1, "no": 55, "date": "1 OCT 19", "date_original": "2019-10-01T20:11:11.000Z", "truespin": 0, "selected": false, "spinAxis": 0, "gyroDegree": "90.0"}, {"_id": "101945@1569960651", "videoPointerID": null, "mode": 1, "spinClockTiltHour": 9, "spinClockTiltMinute": 14, "horizontalAngle": "-5.9", "launchAngle": 2.528379, "rifleSpin": 1585.77527, "pitch_id": 1569960651, "_day": 1, "_month": 10, "_year": 2019, "_hour": 20, "_minute": 10, "_second": 51, "_milisecond": 0, "speed": 77.7, "spin": 2210, "trueSpin": 1539, "spinEfficiency": 69.6, "spinConfidence": 0.8378308, "releaseHeight": 3.797549972963877, "releaseSide": 3.0655177211950204, "releaseExtension": "-", "pitchType": 5, "horizontalBreak": 14.9, "verticalBreak": 0.1, "strike": "Y", "szx": -10.3, "szy": 25.3, "no": 56, "date": "1 OCT 19", "date_original": "2019-10-01T20:10:51.000Z", "truespin": 1539, "selected": false, "spinAxis": "02h:46m", "gyroDegree": "45.9"}, {"_id": "101945@1569960634", "videoPointerID": null, "mode": 1, "spinClockTiltHour": 8, "spinClockTiltMinute": 26, "horizontalAngle": "-5.9", "launchAngle": 2.55698085, "rifleSpin": 1476.41711, "pitch_id": 1569960634, "_day": 1, "_month": 10, "_year": 2019, "_hour": 20, "_minute": 10, "_second": 34, "_milisecond": 0, "speed": 78.3, "spin": 2224, "trueSpin": 1663, "spinEfficiency": 74.8, "spinConfidence": 0.89417696, "releaseHeight": 3.748324907272257, "releaseSide": 3.05699508338679, "releaseExtension": "-", "pitchType": 5, "horizontalBreak": 15.3, "verticalBreak": -6.5, "strike": "N", "szx": -12.5, "szy": 23.2, "no": 57, "date": "1 OCT 19", "date_original": "2019-10-01T20:10:34.000Z", "truespin": 1663, "selected": false, "spinAxis": "03h:34m", "gyroDegree": "41.6"}, {"_id": "101945@1569960609", "videoPointerID": null, "mode": 1, "spinClockTiltHour": 9, "spinClockTiltMinute": 0, "horizontalAngle": "-4.9", "launchAngle": 1.96306694, "rifleSpin": 989.017944, "pitch_id": 1569960609, "_day": 1, "_month": 10, "_year": 2019, "_hour": 20, "_minute": 10, "_second": 9, "_milisecond": 0, "speed": 79.2, "spin": 2150, "trueSpin": 1909, "spinEfficiency": 88.8, "spinConfidence": 0.8272189, "releaseHeight": 3.973683667457322, "releaseSide": 3.10222835117208, "releaseExtension": "-", "pitchType": 0, "horizontalBreak": 19.1, "verticalBreak": -0.9, "strike": "Y", "szx": 7.7, "szy": 25.8, "no": 58, "date": "1 OCT 19", "date_original": "2019-10-01T20:10:09.000Z", "truespin": 1909, "selected": false, "spinAxis": "03h:00m", "gyroDegree": "27.4"}, {"_id": "101945@1569960578", "videoPointerID": null, "mode": 1, "spinClockTiltHour": 8, "spinClockTiltMinute": 38, "horizontalAngle": "-5.3", "launchAngle": 1.828896, "rifleSpin": 1028.45361, "pitch_id": 1569960578, "_day": 1, "_month": 10, "_year": 2019, "_hour": 20, "_minute": 9, "_second": 38, "_milisecond": 0, "speed": 79.6, "spin": 2119, "trueSpin": 1853, "spinEfficiency": 87.4, "spinConfidence": 0.838163435, "releaseHeight": 3.8259645727445997, "releaseSide": 2.97589108063884, "releaseExtension": "-", "pitchType": 0, "horizontalBreak": 18.4, "verticalBreak": -4.6, "strike": "N", "szx": -2.5, "szy": 11.7, "no": 59, "date": "1 OCT 19", "date_original": "2019-10-01T20:09:38.000Z", "truespin": 1853, "selected": false, "spinAxis": "03h:22m", "gyroDegree": "29.0"}, {"_id": "101945@1569960563", "videoPointerID": null, "mode": 1, "spinClockTiltHour": 8, "spinClockTiltMinute": 34, "horizontalAngle": "-4.7", "launchAngle": 3.783625, "rifleSpin": 1245.18884, "pitch_id": 1569960563, "_day": 1, "_month": 10, "_year": 2019, "_hour": 20, "_minute": 9, "_second": 23, "_milisecond": 0, "speed": 77.3, "spin": 2129, "trueSpin": 1727, "spinEfficiency": 81.1, "spinConfidence": 0.8273377, "releaseHeight": 3.6783379649086587, "releaseSide": 3.0341566515935456, "releaseExtension": "-", "pitchType": 0, "horizontalBreak": 16.4, "verticalBreak": -5.1, "strike": "Y", "szx": 5.4, "szy": 30.8, "no": 60, "date": "1 OCT 19", "date_original": "2019-10-01T20:09:23.000Z", "truespin": 1727, "selected": false, "spinAxis": "03h:26m", "gyroDegree": "35.8"}, {"_id": "101945@1569960546", "videoPointerID": null, "mode": 1, "spinClockTiltHour": 9, "spinClockTiltMinute": 2, "horizontalAngle": "-2.3", "launchAngle": 4.04410744, "rifleSpin": 1196.648, "pitch_id": 1569960546, "_day": 1, "_month": 10, "_year": 2019, "_hour": 20, "_minute": 9, "_second": 6, "_milisecond": 0, "speed": 77.4, "spin": 2071, "trueSpin": 0, "spinEfficiency": 0, "spinConfidence": 0, "releaseHeight": 3.4619699527687557, "releaseSide": 2.76085335065319, "releaseExtension": "-", "pitchType": 0, "horizontalBreak": 0, "verticalBreak": 0, "strike": "N", "szx": 12.8, "szy": 9.7, "no": 61, "date": "1 OCT 19", "date_original": "2019-10-01T20:09:06.000Z", "truespin": 0, "selected": false, "spinAxis": 0, "gyroDegree": "90.0"}, {"_id": "101945@1569960523", "videoPointerID": null, "mode": 1, "spinClockTiltHour": 8, "spinClockTiltMinute": 34, "horizontalAngle": "-5.6", "launchAngle": 2.958909, "rifleSpin": 1116.876, "pitch_id": 1569960523, "_day": 1, "_month": 10, "_year": 2019, "_hour": 20, "_minute": 8, "_second": 43, "_milisecond": 0, "speed": 76.8, "spin": 1954, "trueSpin": 1603, "spinEfficiency": 82, "spinConfidence": 0.988681, "releaseHeight": 3.637272544898733, "releaseSide": 2.9834101095216603, "releaseExtension": "-", "pitchType": 0, "horizontalBreak": 16.3, "verticalBreak": -5.3, "strike": "N", "szx": -12.6, "szy": 24.5, "no": 62, "date": "1 OCT 19", "date_original": "2019-10-01T20:08:43.000Z", "truespin": 1603, "selected": false, "spinAxis": "03h:26m", "gyroDegree": "34.9"}, {"_id": "101945@1569960500", "videoPointerID": null, "mode": 1, "spinClockTiltHour": 8, "spinClockTiltMinute": 34, "horizontalAngle": "-5.7", "launchAngle": 3.42587924, "rifleSpin": 1230.48315, "pitch_id": 1569960500, "_day": 1, "_month": 10, "_year": 2019, "_hour": 20, "_minute": 8, "_second": 20, "_milisecond": 0, "speed": 75.2, "spin": 2023, "trueSpin": 1606, "spinEfficiency": 79.4, "spinConfidence": 0.97239095, "releaseHeight": 3.851083076719788, "releaseSide": 3.0221205426513658, "releaseExtension": "-", "pitchType": 0, "horizontalBreak": 16, "verticalBreak": -5.1, "strike": "N", "szx": -12.1, "szy": 29.8, "no": 63, "date": "1 OCT 19", "date_original": "2019-10-01T20:08:20.000Z", "truespin": 1606, "selected": false, "spinAxis": "03h:26m", "gyroDegree": "37.5"}, {"_id": "101945@1569434209", "videoPointerID": null, "mode": 1, "spinClockTiltHour": 8, "spinClockTiltMinute": 58, "horizontalAngle": "-3.6", "launchAngle": 3.13046026, "rifleSpin": 1227.71875, "pitch_id": 1569434209, "_day": 25, "_month": 9, "_year": 2019, "_hour": 17, "_minute": 56, "_second": 49, "_milisecond": 0, "speed": 77.4, "spin": 2032, "trueSpin": 1620, "spinEfficiency": 79.7, "spinConfidence": 0.872233868, "releaseHeight": 3.6478805829726, "releaseSide": 3.18076640903424, "releaseExtension": "-", "pitchType": 5, "horizontalBreak": 15.8, "verticalBreak": -1.2, "strike": "N", "szx": 19, "szy": 32.4, "no": 64, "date": "25 SEP 19", "date_original": "2019-09-25T17:56:49.000Z", "truespin": 1620, "selected": false, "spinAxis": "03h:02m", "gyroDegree": "37.2"}, {"_id": "101945@1569434188", "videoPointerID": null, "mode": 1, "spinClockTiltHour": 8, "spinClockTiltMinute": 58, "horizontalAngle": "-4.9", "launchAngle": 3.25397253, "rifleSpin": 1252.43225, "pitch_id": 1569434188, "_day": 25, "_month": 9, "_year": 2019, "_hour": 17, "_minute": 56, "_second": 28, "_milisecond": 0, "speed": 76.5, "spin": 2001, "trueSpin": 1561, "spinEfficiency": 78, "spinConfidence": 0.7794762, "releaseHeight": 3.687117918990246, "releaseSide": 3.16653510980001, "releaseExtension": "-", "pitchType": 5, "horizontalBreak": 15.6, "verticalBreak": -1.6, "strike": "Y", "szx": 7.7, "szy": 37.5, "no": 65, "date": "25 SEP 19", "date_original": "2019-09-25T17:56:28.000Z", "truespin": 1561, "selected": false, "spinAxis": "03h:02m", "gyroDegree": "38.7"}, {"_id": "101945@1569434174", "videoPointerID": null, "mode": 1, "spinClockTiltHour": 9, "spinClockTiltMinute": 0, "horizontalAngle": "-4.2", "launchAngle": 1.25448513, "rifleSpin": 1306.30725, "pitch_id": 1569434174, "_day": 25, "_month": 9, "_year": 2019, "_hour": 17, "_minute": 56, "_second": 14, "_milisecond": 0, "speed": 77.4, "spin": 2110, "trueSpin": 1657, "spinEfficiency": 78.5, "spinConfidence": 0.9116156, "releaseHeight": 3.679395904542813, "releaseSide": 3.468733601073, "releaseExtension": "-", "pitchType": 5, "horizontalBreak": 16.6, "verticalBreak": -1.1, "strike": "N", "szx": 13, "szy": 9.4, "no": 66, "date": "25 SEP 19", "date_original": "2019-09-25T17:56:14.000Z", "truespin": 1657, "selected": false, "spinAxis": "03h:00m", "gyroDegree": "38.3"}, {"_id": "101945@1569434081", "videoPointerID": null, "mode": 1, "spinClockTiltHour": 8, "spinClockTiltMinute": 54, "horizontalAngle": "-4.4", "launchAngle": 1.251171, "rifleSpin": 934.0416, "pitch_id": 1569434081, "_day": 25, "_month": 9, "_year": 2019, "_hour": 17, "_minute": 54, "_second": 41, "_milisecond": 0, "speed": 79, "spin": 1945, "trueSpin": 1706, "spinEfficiency": 87.7, "spinConfidence": 0.9313894, "releaseHeight": 3.7719082406414373, "releaseSide": 3.1165574194353303, "releaseExtension": "-", "pitchType": 0, "horizontalBreak": 18.1, "verticalBreak": -1.7, "strike": "N", "szx": 6.7, "szy": 11.1, "no": 67, "date": "25 SEP 19", "date_original": "2019-09-25T17:54:41.000Z", "truespin": 1706, "selected": false, "spinAxis": "03h:06m", "gyroDegree": "28.7"}, {"_id": "101945@1569434062", "videoPointerID": null, "mode": 1, "spinClockTiltHour": 9, "spinClockTiltMinute": 40, "horizontalAngle": "-4.6", "launchAngle": 2.84173465, "rifleSpin": 2202.77246, "pitch_id": 1569434062, "_day": 25, "_month": 9, "_year": 2019, "_hour": 17, "_minute": 54, "_second": 22, "_milisecond": 0, "speed": 73.1, "spin": 2226, "trueSpin": 323, "spinEfficiency": 14.5, "spinConfidence": 0.892425239, "releaseHeight": 3.4397805498478893, "releaseSide": 3.09233399420166, "releaseExtension": "-", "pitchType": 4, "horizontalBreak": 1.9, "verticalBreak": -0.6, "strike": "N", "szx": -12.3, "szy": 16.6, "no": 68, "date": "25 SEP 19", "date_original": "2019-09-25T17:54:22.000Z", "truespin": 323, "selected": false, "spinAxis": "02h:20m", "gyroDegree": "81.7"}, {"_id": "101945@1569434046", "videoPointerID": null, "mode": 1, "spinClockTiltHour": 8, "spinClockTiltMinute": 38, "horizontalAngle": "-4.9", "launchAngle": 1.83235538, "rifleSpin": 1274.14429, "pitch_id": 1569434046, "_day": 25, "_month": 9, "_year": 2019, "_hour": 17, "_minute": 54, "_second": 6, "_milisecond": 0, "speed": 76.1, "spin": 2048, "trueSpin": 1603, "spinEfficiency": 78.3, "spinConfidence": 0.8735165, "releaseHeight": 3.5491554515889425, "releaseSide": 3.3029986926846, "releaseExtension": "-", "pitchType": 5, "horizontalBreak": 16.1, "verticalBreak": -4.5, "strike": "N", "szx": 4.7, "szy": 11.9, "no": 69, "date": "25 SEP 19", "date_original": "2019-09-25T17:54:06.000Z", "truespin": 1603, "selected": false, "spinAxis": "03h:22m", "gyroDegree": "38.5"}, {"_id": "101945@1569434029", "videoPointerID": null, "mode": 1, "spinClockTiltHour": 9, "spinClockTiltMinute": 24, "horizontalAngle": "-4.7", "launchAngle": 3.20272446, "rifleSpin": 2035.11133, "pitch_id": 1569434029, "_day": 25, "_month": 9, "_year": 2019, "_hour": 17, "_minute": 53, "_second": 49, "_milisecond": 0, "speed": 73.6, "spin": 2188, "trueSpin": 803, "spinEfficiency": 36.7, "spinConfidence": 0.8916289, "releaseHeight": 3.475543706070228, "releaseSide": 3.14926542473439, "releaseExtension": "-", "pitchType": 4, "horizontalBreak": 7.1, "verticalBreak": 0, "strike": "Y", "szx": -6, "szy": 25.6, "no": 70, "date": "25 SEP 19", "date_original": "2019-09-25T17:53:49.000Z", "truespin": 803, "selected": false, "spinAxis": "02h:36m", "gyroDegree": "68.5"}, {"_id": "101945@1569433989", "videoPointerID": null, "mode": 1, "spinClockTiltHour": 8, "spinClockTiltMinute": 58, "horizontalAngle": "-3.9", "launchAngle": 2.866501, "rifleSpin": 1248.03394, "pitch_id": 1569433989, "_day": 25, "_month": 9, "_year": 2019, "_hour": 17, "_minute": 53, "_second": 9, "_milisecond": 0, "speed": 77.3, "spin": 2047, "trueSpin": 1623, "spinEfficiency": 79.3, "spinConfidence": 0.8999999, "releaseHeight": 3.6215682469746, "releaseSide": 3.1568348604414336, "releaseExtension": "-", "pitchType": 5, "horizontalBreak": 16.2, "verticalBreak": -1.2, "strike": "N", "szx": 10.8, "szy": 23.9, "no": 71, "date": "25 SEP 19", "date_original": "2019-09-25T17:53:09.000Z", "truespin": 1623, "selected": false, "spinAxis": "03h:02m", "gyroDegree": "37.6"}, {"_id": "101945@1569433971", "videoPointerID": null, "mode": 1, "spinClockTiltHour": 9, "spinClockTiltMinute": 6, "horizontalAngle": "-2.5", "launchAngle": 2.04752088, "rifleSpin": 857.356445, "pitch_id": 1569433971, "_day": 25, "_month": 9, "_year": 2019, "_hour": 17, "_minute": 52, "_second": 51, "_milisecond": 0, "speed": 78, "spin": 1972, "trueSpin": 0, "spinEfficiency": 0, "spinConfidence": 0, "releaseHeight": 3.5758598151465932, "releaseSide": 3.1923612253248304, "releaseExtension": "-", "pitchType": 5, "horizontalBreak": 0, "verticalBreak": 0, "strike": "N", "szx": 27.6, "szy": 8.1, "no": 72, "date": "25 SEP 19", "date_original": "2019-09-25T17:52:51.000Z", "truespin": 0, "selected": false, "spinAxis": 0, "gyroDegree": "90.0"}, {"_id": "101945@1569433905", "videoPointerID": null, "mode": 1, "spinClockTiltHour": 8, "spinClockTiltMinute": 38, "horizontalAngle": "-9.4", "launchAngle": 3.582808, "rifleSpin": 1684.13635, "pitch_id": 1569433905, "_day": 25, "_month": 9, "_year": 2019, "_hour": 17, "_minute": 51, "_second": 45, "_milisecond": 0, "speed": 72.7, "spin": 1948, "trueSpin": 0, "spinEfficiency": 0, "spinConfidence": 0, "releaseHeight": 3.295374578499783, "releaseSide": 3.3103969866591, "releaseExtension": "-", "pitchType": 4, "horizontalBreak": 0, "verticalBreak": 0, "strike": "N", "szx": -60, "szy": 26.2, "no": 73, "date": "25 SEP 19", "date_original": "2019-09-25T17:51:45.000Z", "truespin": 0, "selected": false, "spinAxis": 0, "gyroDegree": "90.0"}, {"_id": "101945@1569433854", "videoPointerID": null, "mode": 1, "spinClockTiltHour": 9, "spinClockTiltMinute": 2, "horizontalAngle": "-5.3", "launchAngle": 2.38228464, "rifleSpin": 1963.245, "pitch_id": 1569433854, "_day": 25, "_month": 9, "_year": 2019, "_hour": 17, "_minute": 50, "_second": 54, "_milisecond": 0, "speed": 73.8, "spin": 2110, "trueSpin": 774, "spinEfficiency": 36.7, "spinConfidence": 0.899644732, "releaseHeight": 3.4544579776917215, "releaseSide": 3.2448275869531353, "releaseExtension": "-", "pitchType": 4, "horizontalBreak": 7.4, "verticalBreak": -1.7, "strike": "N", "szx": -18.1, "szy": 13.8, "no": 74, "date": "25 SEP 19", "date_original": "2019-09-25T17:50:54.000Z", "truespin": 774, "selected": false, "spinAxis": "02h:58m", "gyroDegree": "68.5"}, {"_id": "101945@1569433839", "videoPointerID": null, "mode": 1, "spinClockTiltHour": 9, "spinClockTiltMinute": 10, "horizontalAngle": "-6.6", "launchAngle": 2.65722537, "rifleSpin": 1893.30237, "pitch_id": 1569433839, "_day": 25, "_month": 9, "_year": 2019, "_hour": 17, "_minute": 50, "_second": 39, "_milisecond": 0, "speed": 75.3, "spin": 2086, "trueSpin": 0, "spinEfficiency": 0, "spinConfidence": 0, "releaseHeight": 3.524490687771924, "releaseSide": 3.1383990730118363, "releaseExtension": "-", "pitchType": 4, "horizontalBreak": 0, "verticalBreak": 0, "strike": "N", "szx": -27.1, "szy": 16.6, "no": 75, "date": "25 SEP 19", "date_original": "2019-09-25T17:50:39.000Z", "truespin": 0, "selected": false, "spinAxis": 0, "gyroDegree": "90.0"}, {"_id": "101945@1569433820", "videoPointerID": null, "mode": 1, "spinClockTiltHour": 8, "spinClockTiltMinute": 58, "horizontalAngle": "-4.0", "launchAngle": 1.71008563, "rifleSpin": 1138.99231, "pitch_id": 1569433820, "_day": 25, "_month": 9, "_year": 2019, "_hour": 17, "_minute": 50, "_second": 20, "_milisecond": 0, "speed": 78.3, "spin": 1887, "trueSpin": 1504, "spinEfficiency": 79.7, "spinConfidence": 0.8801251, "releaseHeight": 3.6814191000839465, "releaseSide": 3.074362019108726, "releaseExtension": "-", "pitchType": 0, "horizontalBreak": 16, "verticalBreak": -1.2, "strike": "N", "szx": 3.1, "szy": 12.7, "no": 76, "date": "25 SEP 19", "date_original": "2019-09-25T17:50:20.000Z", "truespin": 1504, "selected": false, "spinAxis": "03h:02m", "gyroDegree": "37.1"}, {"_id": "101945@1569433800", "videoPointerID": null, "mode": 1, "spinClockTiltHour": 9, "spinClockTiltMinute": 0, "horizontalAngle": "-2.9", "launchAngle": 2.763569, "rifleSpin": 912.012939, "pitch_id": 1569433800, "_day": 25, "_month": 9, "_year": 2019, "_hour": 17, "_minute": 50, "_second": 0, "_milisecond": 0, "speed": 78.5, "spin": 1885, "trueSpin": 1650, "spinEfficiency": 87.5, "spinConfidence": 0.9717275, "releaseHeight": 3.8221052223450336, "releaseSide": 3.1162751523745333, "releaseExtension": "-", "pitchType": 0, "horizontalBreak": 17.4, "verticalBreak": -0.7, "strike": "N", "szx": 22.6, "szy": 31.5, "no": 77, "date": "25 SEP 19", "date_original": "2019-09-25T17:50:00.000Z", "truespin": 1650, "selected": false, "spinAxis": "03h:00m", "gyroDegree": "28.9"}, {"_id": "101945@1569433779", "videoPointerID": null, "mode": 1, "spinClockTiltHour": 12, "spinClockTiltMinute": 0, "horizontalAngle": "-", "launchAngle": 0, "rifleSpin": 0, "pitch_id": 1569433779, "_day": 25, "_month": 9, "_year": 2019, "_hour": 17, "_minute": 49, "_second": 39, "_milisecond": 0, "speed": 0, "spin": 0, "trueSpin": 0, "spinEfficiency": 0, "spinConfidence": 0, "releaseHeight": 0, "releaseSide": 0, "releaseExtension": "-", "pitchType": 0, "horizontalBreak": 0, "verticalBreak": 0, "strike": "N", "szx": 0, "szy": 0, "no": 78, "date": "25 SEP 19", "date_original": "2019-09-25T17:49:39.000Z", "truespin": 0, "selected": false, "spinAxis": 0, "gyroDegree": "-"}, {"_id": "101945@1569433758", "videoPointerID": null, "mode": 1, "spinClockTiltHour": 8, "spinClockTiltMinute": 38, "horizontalAngle": "-6.3", "launchAngle": 5.005669, "rifleSpin": 1132.796, "pitch_id": 1569433758, "_day": 25, "_month": 9, "_year": 2019, "_hour": 17, "_minute": 49, "_second": 18, "_milisecond": 0, "speed": 76.7, "spin": 1888, "trueSpin": 1510, "spinEfficiency": 80, "spinConfidence": 0.941253066, "releaseHeight": 3.6578018428302, "releaseSide": 3.1814268421061103, "releaseExtension": "-", "pitchType": 0, "horizontalBreak": 15, "verticalBreak": -4.5, "strike": "N", "szx": -19.5, "szy": 52.3, "no": 79, "date": "25 SEP 19", "date_original": "2019-09-25T17:49:18.000Z", "truespin": 1510, "selected": false, "spinAxis": "03h:22m", "gyroDegree": "36.9"}, {"_id": "101945@1569433733", "videoPointerID": null, "mode": 1, "spinClockTiltHour": 8, "spinClockTiltMinute": 42, "horizontalAngle": "-3.1", "launchAngle": 3.59048223, "rifleSpin": 1293.46741, "pitch_id": 1569433733, "_day": 25, "_month": 9, "_year": 2019, "_hour": 17, "_minute": 48, "_second": 53, "_milisecond": 0, "speed": 77.2, "spin": 2123, "trueSpin": 1683, "spinEfficiency": 79.3, "spinConfidence": 0.833710432, "releaseHeight": 3.597088292869149, "releaseSide": 3.272213065997386, "releaseExtension": "-", "pitchType": 5, "horizontalBreak": 15.9, "verticalBreak": -3.4, "strike": "N", "szx": 14.1, "szy": 28.9, "no": 80, "date": "25 SEP 19", "date_original": "2019-09-25T17:48:53.000Z", "truespin": 1683, "selected": false, "spinAxis": "03h:18m", "gyroDegree": "37.5"}, {"_id": "101945@1569433711", "videoPointerID": null, "mode": 1, "spinClockTiltHour": 8, "spinClockTiltMinute": 58, "horizontalAngle": "-4.0", "launchAngle": 2.5297966, "rifleSpin": 1431.519, "pitch_id": 1569433711, "_day": 25, "_month": 9, "_year": 2019, "_hour": 17, "_minute": 48, "_second": 31, "_milisecond": 0, "speed": 77.6, "spin": 1984, "trueSpin": 1373, "spinEfficiency": 69.2, "spinConfidence": 0.9688048, "releaseHeight": 3.7339779584315527, "releaseSide": 3.383318837163642, "releaseExtension": "-", "pitchType": 5, "horizontalBreak": 13.8, "verticalBreak": -1.4, "strike": "Y", "szx": 7.8, "szy": 25.3, "no": 81, "date": "25 SEP 19", "date_original": "2019-09-25T17:48:31.000Z", "truespin": 1373, "selected": false, "spinAxis": "03h:02m", "gyroDegree": "46.2"}, {"_id": "101945@1569433695", "videoPointerID": null, "mode": 1, "spinClockTiltHour": 8, "spinClockTiltMinute": 38, "horizontalAngle": "-5.2", "launchAngle": 1.74034667, "rifleSpin": 1170.254, "pitch_id": 1569433695, "_day": 25, "_month": 9, "_year": 2019, "_hour": 17, "_minute": 48, "_second": 15, "_milisecond": 0, "speed": 77.9, "spin": 1881, "trueSpin": 1472, "spinEfficiency": 78.3, "spinConfidence": 0.8458832, "releaseHeight": 3.7492706093734323, "releaseSide": 3.377776842404562, "releaseExtension": "-", "pitchType": 5, "horizontalBreak": 16, "verticalBreak": -4.4, "strike": "Y", "szx": -3.3, "szy": 21.6, "no": 82, "date": "25 SEP 19", "date_original": "2019-09-25T17:48:15.000Z", "truespin": 1472, "selected": false, "spinAxis": "03h:22m", "gyroDegree": "38.5"}, {"_id": "101945@1569433676", "videoPointerID": null, "mode": 1, "spinClockTiltHour": 9, "spinClockTiltMinute": 0, "horizontalAngle": "-4.3", "launchAngle": 1.79305351, "rifleSpin": 836.470459, "pitch_id": 1569433676, "_day": 25, "_month": 9, "_year": 2019, "_hour": 17, "_minute": 47, "_second": 56, "_milisecond": 0, "speed": 78.9, "spin": 1861, "trueSpin": 1662, "spinEfficiency": 89.3, "spinConfidence": 0.952344358, "releaseHeight": 3.890892656832792, "releaseSide": 3.237450926836936, "releaseExtension": "-", "pitchType": 0, "horizontalBreak": 17.8, "verticalBreak": -0.6, "strike": "Y", "szx": 6.7, "szy": 19.7, "no": 83, "date": "25 SEP 19", "date_original": "2019-09-25T17:47:56.000Z", "truespin": 1662, "selected": false, "spinAxis": "03h:00m", "gyroDegree": "26.7"}, {"_id": "101945@1569433661", "videoPointerID": null, "mode": 1, "spinClockTiltHour": 9, "spinClockTiltMinute": 0, "horizontalAngle": "-5.3", "launchAngle": 3.25507736, "rifleSpin": 1135.5863, "pitch_id": 1569433661, "_day": 25, "_month": 9, "_year": 2019, "_hour": 17, "_minute": 47, "_second": 41, "_milisecond": 0, "speed": 77.7, "spin": 1893, "trueSpin": 1515, "spinEfficiency": 80, "spinConfidence": 0.9697611, "releaseHeight": 3.862114244715558, "releaseSide": 3.357402925050759, "releaseExtension": "-", "pitchType": 0, "horizontalBreak": 15.7, "verticalBreak": -1.2, "strike": "Y", "szx": -4.8, "szy": 37.2, "no": 84, "date": "25 SEP 19", "date_original": "2019-09-25T17:47:41.000Z", "truespin": 1515, "selected": false, "spinAxis": "03h:00m", "gyroDegree": "36.9"}, {"_id": "101945@1569433647", "videoPointerID": null, "mode": 1, "spinClockTiltHour": 8, "spinClockTiltMinute": 58, "horizontalAngle": "-5.1", "launchAngle": 1.88171351, "rifleSpin": 822.534363, "pitch_id": 1569433647, "_day": 25, "_month": 9, "_year": 2019, "_hour": 17, "_minute": 47, "_second": 27, "_milisecond": 0, "speed": 79.1, "spin": 1828, "trueSpin": 1632, "spinEfficiency": 89.3, "spinConfidence": 0.857233167, "releaseHeight": 3.706945838967891, "releaseSide": 3.2952146375546585, "releaseExtension": "-", "pitchType": 0, "horizontalBreak": 17.4, "verticalBreak": -1.2, "strike": "N", "szx": -3.1, "szy": 13.9, "no": 85, "date": "25 SEP 19", "date_original": "2019-09-25T17:47:27.000Z", "truespin": 1632, "selected": false, "spinAxis": "03h:02m", "gyroDegree": "26.7"}, {"_id": "27306@1568314619", "videoPointerID": null, "mode": 1, "spinClockTiltHour": 9, "spinClockTiltMinute": 0, "horizontalAngle": "-2.5", "launchAngle": 2.692123, "memo": null, "rifleSpin": 1544.13831, "pitch_id": 1568314619, "_day": 12, "_month": 9, "_year": 2019, "_hour": 18, "_minute": 56, "_second": 59, "_milisecond": 0, "speed": 77.6, "spin": 2120, "trueSpin": 1453, "spinEfficiency": 68.5, "spinConfidence": 0.875065446, "releaseHeight": 3.6841376696418844, "releaseSide": 1.6222456192637136, "releaseExtension": "-", "pitchType": 0, "horizontalBreak": 14.1, "verticalBreak": -0.8, "strike": "Y", "szx": 9.1, "szy": 24.5, "no": 86, "date": "12 SEP 19", "date_original": "2019-09-12T18:56:59.000Z", "truespin": 1453, "selected": false, "spinAxis": "03h:00m", "gyroDegree": "46.7"}, {"_id": "27306@1568314601", "videoPointerID": null, "mode": 1, "spinClockTiltHour": 9, "spinClockTiltMinute": 0, "horizontalAngle": "-3.3", "launchAngle": 3.74601769, "memo": null, "rifleSpin": 1436.16479, "pitch_id": 1568314601, "_day": 12, "_month": 9, "_year": 2019, "_hour": 18, "_minute": 56, "_second": 41, "_milisecond": 0, "speed": 76.8, "spin": 1991, "trueSpin": 1379, "spinEfficiency": 69.3, "spinConfidence": 0.8169333, "releaseHeight": 3.7034716263641854, "releaseSide": 1.6487114099863565, "releaseExtension": "-", "pitchType": 0, "horizontalBreak": 13.7, "verticalBreak": -0.9, "strike": "N", "szx": 1.6, "szy": 45.2, "no": 87, "date": "12 SEP 19", "date_original": "2019-09-12T18:56:41.000Z", "truespin": 1379, "selected": false, "spinAxis": "03h:00m", "gyroDegree": "46.2"}, {"_id": "27306@1568314553", "videoPointerID": null, "mode": 1, "spinClockTiltHour": 9, "spinClockTiltMinute": 4, "horizontalAngle": "-1.5", "launchAngle": 2.085869, "memo": null, "rifleSpin": 1329.61926, "pitch_id": 1568314553, "_day": 12, "_month": 9, "_year": 2019, "_hour": 18, "_minute": 55, "_second": 53, "_milisecond": 0, "speed": 78.5, "spin": 2094, "trueSpin": 0, "spinEfficiency": 0, "spinConfidence": 0, "releaseHeight": 3.754546626441819, "releaseSide": 1.7998451470927201, "releaseExtension": "-", "pitchType": 0, "horizontalBreak": 0, "verticalBreak": 0, "strike": "N", "szx": 24.9, "szy": 26.4, "no": 88, "date": "12 SEP 19", "date_original": "2019-09-12T18:55:53.000Z", "truespin": 0, "selected": false, "spinAxis": 0, "gyroDegree": "90.0"}, {"_id": "27306@1568314511", "videoPointerID": null, "mode": 1, "spinClockTiltHour": 9, "spinClockTiltMinute": 48, "horizontalAngle": "-3.9", "launchAngle": 3.47634125, "memo": null, "rifleSpin": 2143.569, "pitch_id": 1568314511, "_day": 12, "_month": 9, "_year": 2019, "_hour": 18, "_minute": 55, "_second": 11, "_milisecond": 0, "speed": 73, "spin": 2216, "trueSpin": 564, "spinEfficiency": 25.4, "spinConfidence": 0.7736002, "releaseHeight": 3.459460241478852, "releaseSide": 3.2007068519779356, "releaseExtension": "-", "pitchType": 4, "horizontalBreak": 4, "verticalBreak": 0.8, "strike": "Y", "szx": 3.1, "szy": 40.6, "no": 89, "date": "12 SEP 19", "date_original": "2019-09-12T18:55:11.000Z", "truespin": 564, "selected": false, "spinAxis": "02h:12m", "gyroDegree": "75.3"}, {"_id": "27306@1568314484", "videoPointerID": null, "mode": 1, "spinClockTiltHour": 9, "spinClockTiltMinute": 22, "horizontalAngle": "-6.3", "launchAngle": 1.58243549, "memo": null, "rifleSpin": 2126.14331, "pitch_id": 1568314484, "_day": 12, "_month": 9, "_year": 2019, "_hour": 18, "_minute": 54, "_second": 44, "_milisecond": 0, "speed": 75.5, "spin": 2216, "trueSpin": 0, "spinEfficiency": 0, "spinConfidence": 0, "releaseHeight": 3.6152982338417106, "releaseSide": 3.1743303854024103, "releaseExtension": "-", "pitchType": 4, "horizontalBreak": 0, "verticalBreak": 0, "strike": "N", "szx": -26.8, "szy": 17, "no": 90, "date": "12 SEP 19", "date_original": "2019-09-12T18:54:44.000Z", "truespin": 0, "selected": false, "spinAxis": 0, "gyroDegree": "90.0"}, {"_id": "27306@1568314461", "videoPointerID": null, "mode": 1, "spinClockTiltHour": 9, "spinClockTiltMinute": 2, "horizontalAngle": "-5.9", "launchAngle": 3.31494474, "memo": null, "rifleSpin": 2068.25513, "pitch_id": 1568314461, "_day": 12, "_month": 9, "_year": 2019, "_hour": 18, "_minute": 54, "_second": 21, "_milisecond": 0, "speed": 75.6, "spin": 2236, "trueSpin": 850, "spinEfficiency": 38, "spinConfidence": 0.8016426, "releaseHeight": 3.675582617135442, "releaseSide": 3.2832072556466434, "releaseExtension": "-", "pitchType": 4, "horizontalBreak": 7.4, "verticalBreak": -2.1, "strike": "N", "szx": -15.1, "szy": 40.2, "no": 91, "date": "12 SEP 19", "date_original": "2019-09-12T18:54:21.000Z", "truespin": 850, "selected": false, "spinAxis": "02h:58m", "gyroDegree": "67.7"}, {"_id": "27306@1568314437", "videoPointerID": null, "mode": 1, "spinClockTiltHour": 9, "spinClockTiltMinute": 22, "horizontalAngle": "-4.9", "launchAngle": 2.55341387, "memo": null, "rifleSpin": 2080.46655, "pitch_id": 1568314437, "_day": 12, "_month": 9, "_year": 2019, "_hour": 18, "_minute": 53, "_second": 57, "_milisecond": 0, "speed": 74.6, "spin": 2169, "trueSpin": 614, "spinEfficiency": 28.3, "spinConfidence": 0.9284943, "releaseHeight": 3.37441371903987, "releaseSide": 3.365156599603227, "releaseExtension": "-", "pitchType": 4, "horizontalBreak": 5.2, "verticalBreak": -0.7, "strike": "Y", "szx": -8.9, "szy": 17.8, "no": 92, "date": "12 SEP 19", "date_original": "2019-09-12T18:53:57.000Z", "truespin": 614, "selected": false, "spinAxis": "02h:38m", "gyroDegree": "73.6"}, {"_id": "27306@1568314383", "videoPointerID": null, "mode": 1, "spinClockTiltHour": 9, "spinClockTiltMinute": 20, "horizontalAngle": "-4.5", "launchAngle": 2.47620821, "memo": null, "rifleSpin": 2143.467, "pitch_id": 1568314383, "_day": 12, "_month": 9, "_year": 2019, "_hour": 18, "_minute": 53, "_second": 3, "_milisecond": 0, "speed": 74.8, "spin": 2236, "trueSpin": 0, "spinEfficiency": 0, "spinConfidence": 0, "releaseHeight": 3.4497138503879223, "releaseSide": 1.5857709177647026, "releaseExtension": "-", "pitchType": 4, "horizontalBreak": 0, "verticalBreak": 0, "strike": "N", "szx": -25.7, "szy": 17.6, "no": 93, "date": "12 SEP 19", "date_original": "2019-09-12T18:53:03.000Z", "truespin": 0, "selected": false, "spinAxis": 0, "gyroDegree": "90.0"}, {"_id": "27306@1568314360", "videoPointerID": null, "mode": 1, "spinClockTiltHour": 9, "spinClockTiltMinute": 26, "horizontalAngle": "-0.6", "launchAngle": 3.31956172, "memo": null, "rifleSpin": 2096.19238, "pitch_id": 1568314360, "_day": 12, "_month": 9, "_year": 2019, "_hour": 18, "_minute": 52, "_second": 40, "_milisecond": 0, "speed": 75.6, "spin": 2211, "trueSpin": 0, "spinEfficiency": 0, "spinConfidence": 0, "releaseHeight": 3.5859776957394, "releaseSide": 1.7261428897628448, "releaseExtension": "-", "pitchType": 4, "horizontalBreak": 0, "verticalBreak": 0, "strike": "N", "szx": 23.2, "szy": 36.9, "no": 94, "date": "12 SEP 19", "date_original": "2019-09-12T18:52:40.000Z", "truespin": 0, "selected": false, "spinAxis": 0, "gyroDegree": "90.0"}, {"_id": "27306@1568314323", "videoPointerID": null, "mode": 1, "spinClockTiltHour": 9, "spinClockTiltMinute": 18, "horizontalAngle": "-3.7", "launchAngle": 4.248817, "memo": null, "rifleSpin": 2081.80542, "pitch_id": 1568314323, "_day": 12, "_month": 9, "_year": 2019, "_hour": 18, "_minute": 52, "_second": 3, "_milisecond": 0, "speed": 73.6, "spin": 2218, "trueSpin": 764, "spinEfficiency": 34.5, "spinConfidence": 0.8566934, "releaseHeight": 3.4423064356785003, "releaseSide": 1.6751505930974102, "releaseExtension": "-", "pitchType": 4, "horizontalBreak": 6, "verticalBreak": -0.1, "strike": "N", "szx": -16.6, "szy": 31.1, "no": 95, "date": "12 SEP 19", "date_original": "2019-09-12T18:52:03.000Z", "truespin": 764, "selected": false, "spinAxis": "02h:42m", "gyroDegree": "69.8"}, {"_id": "27306@1568314303", "videoPointerID": null, "mode": 1, "spinClockTiltHour": 9, "spinClockTiltMinute": 44, "horizontalAngle": "-3.0", "launchAngle": 2.184146, "memo": null, "rifleSpin": 2165.48975, "pitch_id": 1568314303, "_day": 12, "_month": 9, "_year": 2019, "_hour": 18, "_minute": 51, "_second": 43, "_milisecond": 0, "speed": 73.8, "spin": 2216, "trueSpin": 469, "spinEfficiency": 21.2, "spinConfidence": 0.769048631, "releaseHeight": 3.590733207557652, "releaseSide": 1.7394207605179353, "releaseExtension": "-", "pitchType": 4, "horizontalBreak": 3.6, "verticalBreak": 0.7, "strike": "Y", "szx": -4.4, "szy": 29.2, "no": 96, "date": "12 SEP 19", "date_original": "2019-09-12T18:51:43.000Z", "truespin": 469, "selected": false, "spinAxis": "02h:16m", "gyroDegree": "77.8"}, {"_id": "27306@1568314279", "videoPointerID": null, "mode": 1, "spinClockTiltHour": 9, "spinClockTiltMinute": 6, "horizontalAngle": "-3.9", "launchAngle": 4.16048145, "memo": null, "rifleSpin": 2005.15747, "pitch_id": 1568314279, "_day": 12, "_month": 9, "_year": 2019, "_hour": 18, "_minute": 51, "_second": 19, "_milisecond": 0, "speed": 73.1, "spin": 2094, "trueSpin": 603, "spinEfficiency": 28.8, "spinConfidence": 0.851552248, "releaseHeight": 3.3676687059062584, "releaseSide": 1.5604494774375002, "releaseExtension": "-", "pitchType": 4, "horizontalBreak": 4.7, "verticalBreak": -1, "strike": "N", "szx": -16.6, "szy": 28.9, "no": 97, "date": "12 SEP 19", "date_original": "2019-09-12T18:51:19.000Z", "truespin": 603, "selected": false, "spinAxis": "02h:54m", "gyroDegree": "73.3"}, {"_id": "27306@1568314258", "videoPointerID": null, "mode": 1, "spinClockTiltHour": 9, "spinClockTiltMinute": 4, "horizontalAngle": "-4.1", "launchAngle": 2.789605, "memo": null, "rifleSpin": 1261.69519, "pitch_id": 1568314258, "_day": 12, "_month": 9, "_year": 2019, "_hour": 18, "_minute": 50, "_second": 58, "_milisecond": 0, "speed": 79.1, "spin": 1983, "trueSpin": 1530, "spinEfficiency": 77.1, "spinConfidence": 0.9266339, "releaseHeight": 3.70461877203522, "releaseSide": 1.64801542245249, "releaseExtension": "-", "pitchType": 0, "horizontalBreak": 15.6, "verticalBreak": -0.4, "strike": "Y", "szx": -9.5, "szy": 29.8, "no": 98, "date": "12 SEP 19", "date_original": "2019-09-12T18:50:58.000Z", "truespin": 1530, "selected": false, "spinAxis": "02h:56m", "gyroDegree": "39.5"}, {"_id": "27306@1568314239", "videoPointerID": null, "mode": 1, "spinClockTiltHour": 9, "spinClockTiltMinute": 0, "horizontalAngle": "-5.1", "launchAngle": 2.21052957, "memo": null, "rifleSpin": 904.129456, "pitch_id": 1568314239, "_day": 12, "_month": 9, "_year": 2019, "_hour": 18, "_minute": 50, "_second": 39, "_milisecond": 0, "speed": 78.4, "spin": 1932, "trueSpin": 1708, "spinEfficiency": 88.4, "spinConfidence": 0.791440368, "releaseHeight": 3.5262204778008, "releaseSide": 1.72473261417015, "releaseExtension": "-", "pitchType": 0, "horizontalBreak": 17.8, "verticalBreak": -1, "strike": "N", "szx": -13.1, "szy": 13.3, "no": 99, "date": "12 SEP 19", "date_original": "2019-09-12T18:50:39.000Z", "truespin": 1708, "selected": false, "spinAxis": "03h:00m", "gyroDegree": "27.9"}, {"_id": "27306@1568314222", "videoPointerID": null, "mode": 1, "spinClockTiltHour": 8, "spinClockTiltMinute": 56, "horizontalAngle": "-2.5", "launchAngle": 3.60189223, "memo": null, "rifleSpin": 1631.18115, "pitch_id": 1568314222, "_day": 12, "_month": 9, "_year": 2019, "_hour": 18, "_minute": 50, "_second": 22, "_milisecond": 0, "speed": 76.4, "spin": 2070, "trueSpin": 1274, "spinEfficiency": 61.6, "spinConfidence": 0.866334856, "releaseHeight": 3.5829712980970347, "releaseSide": 1.7858848452342302, "releaseExtension": "-", "pitchType": 5, "horizontalBreak": 12.3, "verticalBreak": -1.2, "strike": "Y", "szx": 9.3, "szy": 39.6, "no": 100, "date": "12 SEP 19", "date_original": "2019-09-12T18:50:22.000Z", "truespin": 1274, "selected": false, "spinAxis": "03h:04m", "gyroDegree": "52.0"}, {"_id": "27306@1568314200", "videoPointerID": null, "mode": 1, "spinClockTiltHour": 9, "spinClockTiltMinute": 8, "horizontalAngle": "-2.7", "launchAngle": 1.84628677, "memo": null, "rifleSpin": 1387.13257, "pitch_id": 1568314200, "_day": 12, "_month": 9, "_year": 2019, "_hour": 18, "_minute": 50, "_second": 0, "_milisecond": 0, "speed": 79.1, "spin": 2081, "trueSpin": 1551, "spinEfficiency": 74.5, "spinConfidence": 0.956672966, "releaseHeight": 3.7263959702310516, "releaseSide": 1.6783503962518802, "releaseExtension": "-", "pitchType": 5, "horizontalBreak": 15.5, "verticalBreak": 0.2, "strike": "Y", "szx": 5.5, "szy": 19.1, "no": 101, "date": "12 SEP 19", "date_original": "2019-09-12T18:50:00.000Z", "truespin": 1551, "selected": false, "spinAxis": "02h:52m", "gyroDegree": "41.8"}, {"_id": "27306@1568314021", "videoPointerID": null, "mode": 1, "spinClockTiltHour": 8, "spinClockTiltMinute": 34, "horizontalAngle": "-4.0", "launchAngle": 2.17106152, "memo": null, "rifleSpin": 1108.48547, "pitch_id": 1568314021, "_day": 12, "_month": 9, "_year": 2019, "_hour": 18, "_minute": 47, "_second": 1, "_milisecond": 0, "speed": 79.9, "spin": 1795, "trueSpin": 1412, "spinEfficiency": 78.7, "spinConfidence": 0.8456015, "releaseHeight": 3.657085996372419, "releaseSide": 1.5475917772867227, "releaseExtension": "-", "pitchType": 0, "horizontalBreak": 14.8, "verticalBreak": -4.6, "strike": "Y", "szx": -7.1, "szy": 16.2, "no": 102, "date": "12 SEP 19", "date_original": "2019-09-12T18:47:01.000Z", "truespin": 1412, "selected": false, "spinAxis": "03h:26m", "gyroDegree": "38.1"}, {"_id": "27306@1568314004", "videoPointerID": null, "mode": 1, "spinClockTiltHour": 9, "spinClockTiltMinute": 6, "horizontalAngle": "-2.5", "launchAngle": 2.53967, "memo": null, "rifleSpin": 1202.872, "pitch_id": 1568314004, "_day": 12, "_month": 9, "_year": 2019, "_hour": 18, "_minute": 46, "_second": 44, "_milisecond": 0, "speed": 79.6, "spin": 1907, "trueSpin": 1480, "spinEfficiency": 77.6, "spinConfidence": 0.838309169, "releaseHeight": 3.8173540740438483, "releaseSide": 1.6461384539457002, "releaseExtension": "-", "pitchType": 0, "horizontalBreak": 15.2, "verticalBreak": 0.1, "strike": "N", "szx": 12.8, "szy": 30.2, "no": 103, "date": "12 SEP 19", "date_original": "2019-09-12T18:46:44.000Z", "truespin": 1480, "selected": false, "spinAxis": "02h:54m", "gyroDegree": "39.1"}, {"_id": "27306@1568313951", "videoPointerID": null, "mode": 1, "spinClockTiltHour": 8, "spinClockTiltMinute": 56, "horizontalAngle": "-3.3", "launchAngle": 3.14815354, "memo": null, "rifleSpin": 1277.55579, "pitch_id": 1568313951, "_day": 12, "_month": 9, "_year": 2019, "_hour": 18, "_minute": 45, "_second": 51, "_milisecond": 0, "speed": 79, "spin": 1989, "trueSpin": 1524, "spinEfficiency": 76.6, "spinConfidence": 0.90549, "releaseHeight": 3.778152269522319, "releaseSide": 1.5550311145683717, "releaseExtension": "-", "pitchType": 0, "horizontalBreak": 15.5, "verticalBreak": -1.4, "strike": "Y", "szx": -1.3, "szy": 37.5, "no": 104, "date": "12 SEP 19", "date_original": "2019-09-12T18:45:51.000Z", "truespin": 1524, "selected": false, "spinAxis": "03h:04m", "gyroDegree": "40.0"}, {"_id": "27306@1568313927", "videoPointerID": null, "mode": 1, "spinClockTiltHour": 8, "spinClockTiltMinute": 50, "horizontalAngle": "-0.9", "launchAngle": 1.39550519, "memo": null, "rifleSpin": 864.047363, "pitch_id": 1568313927, "_day": 12, "_month": 9, "_year": 2019, "_hour": 18, "_minute": 45, "_second": 27, "_milisecond": 0, "speed": 78.4, "spin": 1802, "trueSpin": 0, "spinEfficiency": 0, "spinConfidence": 0, "releaseHeight": 3.877379533452672, "releaseSide": 1.6690624467626967, "releaseExtension": "-", "pitchType": 0, "horizontalBreak": 0, "verticalBreak": 0, "strike": "N", "szx": 30.7, "szy": 24, "no": 105, "date": "12 SEP 19", "date_original": "2019-09-12T18:45:27.000Z", "truespin": 0, "selected": false, "spinAxis": 0, "gyroDegree": "90.0"}, {"_id": "27306@1568313905", "videoPointerID": null, "mode": 1, "spinClockTiltHour": 8, "spinClockTiltMinute": 52, "horizontalAngle": "-1.0", "launchAngle": 2.187259, "memo": null, "rifleSpin": 887.7057, "pitch_id": 1568313905, "_day": 12, "_month": 9, "_year": 2019, "_hour": 18, "_minute": 45, "_second": 5, "_milisecond": 0, "speed": 79.1, "spin": 1823, "trueSpin": 0, "spinEfficiency": 0, "spinConfidence": 0, "releaseHeight": 3.4803296968911512, "releaseSide": 1.669280681671165, "releaseExtension": "-", "pitchType": 0, "horizontalBreak": 0, "verticalBreak": 0, "strike": "N", "szx": 27, "szy": 14, "no": 106, "date": "12 SEP 19", "date_original": "2019-09-12T18:45:05.000Z", "truespin": 0, "selected": false, "spinAxis": 0, "gyroDegree": "90.0"}, {"_id": "27306@1568313883", "videoPointerID": null, "mode": 1, "spinClockTiltHour": 8, "spinClockTiltMinute": 52, "horizontalAngle": "-3.3", "launchAngle": 4.56840134, "memo": null, "rifleSpin": 1076.25659, "pitch_id": 1568313883, "_day": 12, "_month": 9, "_year": 2019, "_hour": 18, "_minute": 44, "_second": 43, "_milisecond": 0, "speed": 77.7, "spin": 1813, "trueSpin": 1460, "spinEfficiency": 80.5, "spinConfidence": 0.821954, "releaseHeight": 3.641183601335124, "releaseSide": 1.75145472707166, "releaseExtension": "-", "pitchType": 0, "horizontalBreak": 15.4, "verticalBreak": -1.8, "strike": "N", "szx": 5.7, "szy": 52.7, "no": 107, "date": "12 SEP 19", "date_original": "2019-09-12T18:44:43.000Z", "truespin": 1460, "selected": false, "spinAxis": "03h:08m", "gyroDegree": "36.4"}, {"_id": "27306@1568313838", "videoPointerID": null, "mode": 1, "spinClockTiltHour": 9, "spinClockTiltMinute": 0, "horizontalAngle": "-2.3", "launchAngle": 2.82052183, "memo": null, "rifleSpin": 1108.82922, "pitch_id": 1568313838, "_day": 12, "_month": 9, "_year": 2019, "_hour": 18, "_minute": 43, "_second": 58, "_milisecond": 0, "speed": 77, "spin": 1832, "trueSpin": 1459, "spinEfficiency": 79.6, "spinConfidence": 0.829049766, "releaseHeight": 3.6825783192458132, "releaseSide": 1.6341254814864954, "releaseExtension": "-", "pitchType": 0, "horizontalBreak": 15.7, "verticalBreak": -0.6, "strike": "N", "szx": 16.2, "szy": 27.3, "no": 108, "date": "12 SEP 19", "date_original": "2019-09-12T18:43:58.000Z", "truespin": 1459, "selected": false, "spinAxis": "03h:00m", "gyroDegree": "37.2"}, {"_id": "27306@1568313822", "videoPointerID": null, "mode": 1, "spinClockTiltHour": 8, "spinClockTiltMinute": 56, "horizontalAngle": "-2.2", "launchAngle": 2.10135221, "memo": null, "rifleSpin": 1199.873, "pitch_id": 1568313822, "_day": 12, "_month": 9, "_year": 2019, "_hour": 18, "_minute": 43, "_second": 42, "_milisecond": 0, "speed": 77.3, "spin": 1809, "trueSpin": 1354, "spinEfficiency": 74.8, "spinConfidence": 0.8594261, "releaseHeight": 3.7576930831395154, "releaseSide": 1.6506843857111402, "releaseExtension": "-", "pitchType": 0, "horizontalBreak": 15.1, "verticalBreak": -1.2, "strike": "N", "szx": 14.3, "szy": 21, "no": 109, "date": "12 SEP 19", "date_original": "2019-09-12T18:43:42.000Z", "truespin": 1354, "selected": false, "spinAxis": "03h:04m", "gyroDegree": "41.5"}, {"_id": "27306@1568313803", "videoPointerID": null, "mode": 1, "spinClockTiltHour": 8, "spinClockTiltMinute": 26, "horizontalAngle": "-3.7", "launchAngle": 2.539561, "memo": null, "rifleSpin": 1086.77649, "pitch_id": 1568313803, "_day": 12, "_month": 9, "_year": 2019, "_hour": 18, "_minute": 43, "_second": 23, "_milisecond": 0, "speed": 74.6, "spin": 1822, "trueSpin": 1462, "spinEfficiency": 80.3, "spinConfidence": 0.888064265, "releaseHeight": 3.513145084080138, "releaseSide": 1.59170144598894, "releaseExtension": "-", "pitchType": 0, "horizontalBreak": 15.6, "verticalBreak": -5.7, "strike": "Y", "szx": -4.2, "szy": 15.4, "no": 110, "date": "12 SEP 19", "date_original": "2019-09-12T18:43:23.000Z", "truespin": 1462, "selected": false, "spinAxis": "03h:34m", "gyroDegree": "36.6"}, {"_id": "27306@1568313784", "videoPointerID": null, "mode": 1, "spinClockTiltHour": 8, "spinClockTiltMinute": 24, "horizontalAngle": "-1.9", "launchAngle": 2.27816558, "memo": null, "rifleSpin": 1170.14307, "pitch_id": 1568313784, "_day": 12, "_month": 9, "_year": 2019, "_hour": 18, "_minute": 43, "_second": 4, "_milisecond": 0, "speed": 74.4, "spin": 1858, "trueSpin": 0, "spinEfficiency": 0, "spinConfidence": 0, "releaseHeight": 3.513679336049454, "releaseSide": 1.7023267742410801, "releaseExtension": "-", "pitchType": 0, "horizontalBreak": 0, "verticalBreak": 0, "strike": "N", "szx": 22, "szy": 19.6, "no": 111, "date": "12 SEP 19", "date_original": "2019-09-12T18:43:04.000Z", "truespin": 0, "selected": false, "spinAxis": 0, "gyroDegree": "90.0"}, {"_id": "27306@1568313769", "videoPointerID": null, "mode": 1, "spinClockTiltHour": 9, "spinClockTiltMinute": 42, "horizontalAngle": "-1.3", "launchAngle": 0.2646543, "memo": null, "rifleSpin": 807.412354, "pitch_id": 1568313769, "_day": 12, "_month": 9, "_year": 2019, "_hour": 18, "_minute": 42, "_second": 49, "_milisecond": 0, "speed": 74.9, "spin": 1263, "trueSpin": 0, "spinEfficiency": 0, "spinConfidence": 0, "releaseHeight": 3.9155202487337433, "releaseSide": 1.7852078078316262, "releaseExtension": "-", "pitchType": 0, "horizontalBreak": 0, "verticalBreak": 0, "strike": "N", "szx": 40.2, "szy": 24.9, "no": 112, "date": "12 SEP 19", "date_original": "2019-09-12T18:42:49.000Z", "truespin": 0, "selected": false, "spinAxis": 0, "gyroDegree": "90.0"}, {"_id": "27306@1568309438", "videoPointerID": null, "mode": 1, "spinClockTiltHour": 12, "spinClockTiltMinute": 0, "horizontalAngle": "-", "launchAngle": 0, "memo": null, "rifleSpin": 0, "pitch_id": 1568309438, "_day": 12, "_month": 9, "_year": 2019, "_hour": 17, "_minute": 30, "_second": 38, "_milisecond": 0, "speed": 0, "spin": 0, "trueSpin": 0, "spinEfficiency": 0, "spinConfidence": 0, "releaseHeight": 0, "releaseSide": 0, "releaseExtension": "-", "pitchType": 0, "horizontalBreak": 0, "verticalBreak": 0, "strike": "N", "szx": 0, "szy": 0, "no": 113, "date": "12 SEP 19", "date_original": "2019-09-12T17:30:38.000Z", "truespin": 0, "selected": false, "spinAxis": 0, "gyroDegree": "-"}]